[{"name":"ailia_tokenizer","qualifiedName":"ailia_tokenizer","href":"ailia_tokenizer/","kind":9,"packageRank":0,"desc":""},{"name":"AILIAEnvironment","qualifiedName":"ailia_tokenizer.AILIAEnvironment","href":"ailia_tokenizer/AILIAEnvironment.html","kind":21,"packageRank":0,"desc":"","enclosedBy":{"name":"ailia_tokenizer","kind":9,"href":"ailia_tokenizer/"}},{"name":"AILIANetwork","qualifiedName":"ailia_tokenizer.AILIANetwork","href":"ailia_tokenizer/AILIANetwork-class.html","kind":3,"packageRank":0,"desc":"ネットワークオブジェクトのインスタンス","enclosedBy":{"name":"ailia_tokenizer","kind":9,"href":"ailia_tokenizer/"}},{"name":"AILIANetwork.new","qualifiedName":"ailia_tokenizer.AILIANetwork.AILIANetwork.new","href":"ailia_tokenizer/AILIANetwork/AILIANetwork.html","kind":2,"packageRank":0,"desc":"","enclosedBy":{"name":"AILIANetwork","kind":3,"href":"ailia_tokenizer/AILIANetwork-class.html"}},{"name":"AILIAShape","qualifiedName":"ailia_tokenizer.AILIAShape","href":"ailia_tokenizer/AILIAShape.html","kind":21,"packageRank":0,"desc":"","enclosedBy":{"name":"ailia_tokenizer","kind":9,"href":"ailia_tokenizer/"}},{"name":"AILIATokenizer","qualifiedName":"ailia_tokenizer.AILIATokenizer","href":"ailia_tokenizer/AILIATokenizer-class.html","kind":3,"packageRank":0,"desc":"トークナイズオブジェクトのインスタンス","enclosedBy":{"name":"ailia_tokenizer","kind":9,"href":"ailia_tokenizer/"}},{"name":"AILIATokenizer.new","qualifiedName":"ailia_tokenizer.AILIATokenizer.AILIATokenizer.new","href":"ailia_tokenizer/AILIATokenizer/AILIATokenizer.html","kind":2,"packageRank":0,"desc":"","enclosedBy":{"name":"AILIATokenizer","kind":3,"href":"ailia_tokenizer/AILIATokenizer-class.html"}},{"name":"AILIA_DATATYPE_BFLOAT16","qualifiedName":"ailia_tokenizer.AILIA_DATATYPE_BFLOAT16","href":"ailia_tokenizer/AILIA_DATATYPE_BFLOAT16-constant.html","kind":19,"packageRank":0,"desc":"","enclosedBy":{"name":"ailia_tokenizer","kind":9,"href":"ailia_tokenizer/"}},{"name":"AILIA_DATATYPE_BOOL","qualifiedName":"ailia_tokenizer.AILIA_DATATYPE_BOOL","href":"ailia_tokenizer/AILIA_DATATYPE_BOOL-constant.html","kind":19,"packageRank":0,"desc":"","enclosedBy":{"name":"ailia_tokenizer","kind":9,"href":"ailia_tokenizer/"}},{"name":"AILIA_DATATYPE_DOUBLE","qualifiedName":"ailia_tokenizer.AILIA_DATATYPE_DOUBLE","href":"ailia_tokenizer/AILIA_DATATYPE_DOUBLE-constant.html","kind":19,"packageRank":0,"desc":"","enclosedBy":{"name":"ailia_tokenizer","kind":9,"href":"ailia_tokenizer/"}},{"name":"AILIA_DATATYPE_FLOAT","qualifiedName":"ailia_tokenizer.AILIA_DATATYPE_FLOAT","href":"ailia_tokenizer/AILIA_DATATYPE_FLOAT-constant.html","kind":19,"packageRank":0,"desc":"","enclosedBy":{"name":"ailia_tokenizer","kind":9,"href":"ailia_tokenizer/"}},{"name":"AILIA_DATATYPE_FLOAT16","qualifiedName":"ailia_tokenizer.AILIA_DATATYPE_FLOAT16","href":"ailia_tokenizer/AILIA_DATATYPE_FLOAT16-constant.html","kind":19,"packageRank":0,"desc":"","enclosedBy":{"name":"ailia_tokenizer","kind":9,"href":"ailia_tokenizer/"}},{"name":"AILIA_DATATYPE_INT8","qualifiedName":"ailia_tokenizer.AILIA_DATATYPE_INT8","href":"ailia_tokenizer/AILIA_DATATYPE_INT8-constant.html","kind":19,"packageRank":0,"desc":"","enclosedBy":{"name":"ailia_tokenizer","kind":9,"href":"ailia_tokenizer/"}},{"name":"AILIA_DATATYPE_INT16","qualifiedName":"ailia_tokenizer.AILIA_DATATYPE_INT16","href":"ailia_tokenizer/AILIA_DATATYPE_INT16-constant.html","kind":19,"packageRank":0,"desc":"","enclosedBy":{"name":"ailia_tokenizer","kind":9,"href":"ailia_tokenizer/"}},{"name":"AILIA_DATATYPE_INT32","qualifiedName":"ailia_tokenizer.AILIA_DATATYPE_INT32","href":"ailia_tokenizer/AILIA_DATATYPE_INT32-constant.html","kind":19,"packageRank":0,"desc":"","enclosedBy":{"name":"ailia_tokenizer","kind":9,"href":"ailia_tokenizer/"}},{"name":"AILIA_DATATYPE_INT64","qualifiedName":"ailia_tokenizer.AILIA_DATATYPE_INT64","href":"ailia_tokenizer/AILIA_DATATYPE_INT64-constant.html","kind":19,"packageRank":0,"desc":"","enclosedBy":{"name":"ailia_tokenizer","kind":9,"href":"ailia_tokenizer/"}},{"name":"AILIA_DATATYPE_UINT8","qualifiedName":"ailia_tokenizer.AILIA_DATATYPE_UINT8","href":"ailia_tokenizer/AILIA_DATATYPE_UINT8-constant.html","kind":19,"packageRank":0,"desc":"","enclosedBy":{"name":"ailia_tokenizer","kind":9,"href":"ailia_tokenizer/"}},{"name":"AILIA_DATATYPE_UINT16","qualifiedName":"ailia_tokenizer.AILIA_DATATYPE_UINT16","href":"ailia_tokenizer/AILIA_DATATYPE_UINT16-constant.html","kind":19,"packageRank":0,"desc":"","enclosedBy":{"name":"ailia_tokenizer","kind":9,"href":"ailia_tokenizer/"}},{"name":"AILIA_DATATYPE_UINT32","qualifiedName":"ailia_tokenizer.AILIA_DATATYPE_UINT32","href":"ailia_tokenizer/AILIA_DATATYPE_UINT32-constant.html","kind":19,"packageRank":0,"desc":"","enclosedBy":{"name":"ailia_tokenizer","kind":9,"href":"ailia_tokenizer/"}},{"name":"AILIA_DATATYPE_UINT64","qualifiedName":"ailia_tokenizer.AILIA_DATATYPE_UINT64","href":"ailia_tokenizer/AILIA_DATATYPE_UINT64-constant.html","kind":19,"packageRank":0,"desc":"","enclosedBy":{"name":"ailia_tokenizer","kind":9,"href":"ailia_tokenizer/"}},{"name":"AILIA_DATATYPE_UNDEFINED","qualifiedName":"ailia_tokenizer.AILIA_DATATYPE_UNDEFINED","href":"ailia_tokenizer/AILIA_DATATYPE_UNDEFINED-constant.html","kind":19,"packageRank":0,"desc":"","enclosedBy":{"name":"ailia_tokenizer","kind":9,"href":"ailia_tokenizer/"}},{"name":"AILIA_ENVIRONMENT_BACKEND_CUDA","qualifiedName":"ailia_tokenizer.AILIA_ENVIRONMENT_BACKEND_CUDA","href":"ailia_tokenizer/AILIA_ENVIRONMENT_BACKEND_CUDA-constant.html","kind":19,"packageRank":0,"desc":"","enclosedBy":{"name":"ailia_tokenizer","kind":9,"href":"ailia_tokenizer/"}},{"name":"AILIA_ENVIRONMENT_BACKEND_MPS","qualifiedName":"ailia_tokenizer.AILIA_ENVIRONMENT_BACKEND_MPS","href":"ailia_tokenizer/AILIA_ENVIRONMENT_BACKEND_MPS-constant.html","kind":19,"packageRank":0,"desc":"","enclosedBy":{"name":"ailia_tokenizer","kind":9,"href":"ailia_tokenizer/"}},{"name":"AILIA_ENVIRONMENT_BACKEND_NONE","qualifiedName":"ailia_tokenizer.AILIA_ENVIRONMENT_BACKEND_NONE","href":"ailia_tokenizer/AILIA_ENVIRONMENT_BACKEND_NONE-constant.html","kind":19,"packageRank":0,"desc":"","enclosedBy":{"name":"ailia_tokenizer","kind":9,"href":"ailia_tokenizer/"}},{"name":"AILIA_ENVIRONMENT_BACKEND_VULKAN","qualifiedName":"ailia_tokenizer.AILIA_ENVIRONMENT_BACKEND_VULKAN","href":"ailia_tokenizer/AILIA_ENVIRONMENT_BACKEND_VULKAN-constant.html","kind":19,"packageRank":0,"desc":"","enclosedBy":{"name":"ailia_tokenizer","kind":9,"href":"ailia_tokenizer/"}},{"name":"AILIA_ENVIRONMENT_ID_AUTO","qualifiedName":"ailia_tokenizer.AILIA_ENVIRONMENT_ID_AUTO","href":"ailia_tokenizer/AILIA_ENVIRONMENT_ID_AUTO-constant.html","kind":19,"packageRank":0,"desc":"","enclosedBy":{"name":"ailia_tokenizer","kind":9,"href":"ailia_tokenizer/"}},{"name":"AILIA_ENVIRONMENT_PROPERTY_FP16","qualifiedName":"ailia_tokenizer.AILIA_ENVIRONMENT_PROPERTY_FP16","href":"ailia_tokenizer/AILIA_ENVIRONMENT_PROPERTY_FP16-constant.html","kind":19,"packageRank":0,"desc":"","enclosedBy":{"name":"ailia_tokenizer","kind":9,"href":"ailia_tokenizer/"}},{"name":"AILIA_ENVIRONMENT_PROPERTY_LOWPOWER","qualifiedName":"ailia_tokenizer.AILIA_ENVIRONMENT_PROPERTY_LOWPOWER","href":"ailia_tokenizer/AILIA_ENVIRONMENT_PROPERTY_LOWPOWER-constant.html","kind":19,"packageRank":0,"desc":"","enclosedBy":{"name":"ailia_tokenizer","kind":9,"href":"ailia_tokenizer/"}},{"name":"AILIA_ENVIRONMENT_PROPERTY_NORMAL","qualifiedName":"ailia_tokenizer.AILIA_ENVIRONMENT_PROPERTY_NORMAL","href":"ailia_tokenizer/AILIA_ENVIRONMENT_PROPERTY_NORMAL-constant.html","kind":19,"packageRank":0,"desc":"","enclosedBy":{"name":"ailia_tokenizer","kind":9,"href":"ailia_tokenizer/"}},{"name":"AILIA_ENVIRONMENT_TYPE_BLAS","qualifiedName":"ailia_tokenizer.AILIA_ENVIRONMENT_TYPE_BLAS","href":"ailia_tokenizer/AILIA_ENVIRONMENT_TYPE_BLAS-constant.html","kind":19,"packageRank":0,"desc":"","enclosedBy":{"name":"ailia_tokenizer","kind":9,"href":"ailia_tokenizer/"}},{"name":"AILIA_ENVIRONMENT_TYPE_CPU","qualifiedName":"ailia_tokenizer.AILIA_ENVIRONMENT_TYPE_CPU","href":"ailia_tokenizer/AILIA_ENVIRONMENT_TYPE_CPU-constant.html","kind":19,"packageRank":0,"desc":"","enclosedBy":{"name":"ailia_tokenizer","kind":9,"href":"ailia_tokenizer/"}},{"name":"AILIA_ENVIRONMENT_TYPE_GPU","qualifiedName":"ailia_tokenizer.AILIA_ENVIRONMENT_TYPE_GPU","href":"ailia_tokenizer/AILIA_ENVIRONMENT_TYPE_GPU-constant.html","kind":19,"packageRank":0,"desc":"","enclosedBy":{"name":"ailia_tokenizer","kind":9,"href":"ailia_tokenizer/"}},{"name":"AILIA_ENVIRONMENT_TYPE_REMOTE","qualifiedName":"ailia_tokenizer.AILIA_ENVIRONMENT_TYPE_REMOTE","href":"ailia_tokenizer/AILIA_ENVIRONMENT_TYPE_REMOTE-constant.html","kind":19,"packageRank":0,"desc":"","enclosedBy":{"name":"ailia_tokenizer","kind":9,"href":"ailia_tokenizer/"}},{"name":"AILIA_ENVIRONMENT_VERSION","qualifiedName":"ailia_tokenizer.AILIA_ENVIRONMENT_VERSION","href":"ailia_tokenizer/AILIA_ENVIRONMENT_VERSION-constant.html","kind":19,"packageRank":0,"desc":"","enclosedBy":{"name":"ailia_tokenizer","kind":9,"href":"ailia_tokenizer/"}},{"name":"AILIA_FILE_CALLBACK_VERSION","qualifiedName":"ailia_tokenizer.AILIA_FILE_CALLBACK_VERSION","href":"ailia_tokenizer/AILIA_FILE_CALLBACK_VERSION-constant.html","kind":19,"packageRank":0,"desc":"","enclosedBy":{"name":"ailia_tokenizer","kind":9,"href":"ailia_tokenizer/"}},{"name":"AILIA_MEMORY_NO_OPTIMIZATION","qualifiedName":"ailia_tokenizer.AILIA_MEMORY_NO_OPTIMIZATION","href":"ailia_tokenizer/AILIA_MEMORY_NO_OPTIMIZATION-constant.html","kind":19,"packageRank":0,"desc":"","enclosedBy":{"name":"ailia_tokenizer","kind":9,"href":"ailia_tokenizer/"}},{"name":"AILIA_MEMORY_OPTIMAIZE_DEFAULT","qualifiedName":"ailia_tokenizer.AILIA_MEMORY_OPTIMAIZE_DEFAULT","href":"ailia_tokenizer/AILIA_MEMORY_OPTIMAIZE_DEFAULT-constant.html","kind":19,"packageRank":0,"desc":"","enclosedBy":{"name":"ailia_tokenizer","kind":9,"href":"ailia_tokenizer/"}},{"name":"AILIA_MEMORY_REDUCE_CONSTANT","qualifiedName":"ailia_tokenizer.AILIA_MEMORY_REDUCE_CONSTANT","href":"ailia_tokenizer/AILIA_MEMORY_REDUCE_CONSTANT-constant.html","kind":19,"packageRank":0,"desc":"","enclosedBy":{"name":"ailia_tokenizer","kind":9,"href":"ailia_tokenizer/"}},{"name":"AILIA_MEMORY_REDUCE_CONSTANT_WITH_FILE_MAPPED","qualifiedName":"ailia_tokenizer.AILIA_MEMORY_REDUCE_CONSTANT_WITH_FILE_MAPPED","href":"ailia_tokenizer/AILIA_MEMORY_REDUCE_CONSTANT_WITH_FILE_MAPPED-constant.html","kind":19,"packageRank":0,"desc":"","enclosedBy":{"name":"ailia_tokenizer","kind":9,"href":"ailia_tokenizer/"}},{"name":"AILIA_MEMORY_REDUCE_CONSTANT_WITH_INPUT_INITIALIZER","qualifiedName":"ailia_tokenizer.AILIA_MEMORY_REDUCE_CONSTANT_WITH_INPUT_INITIALIZER","href":"ailia_tokenizer/AILIA_MEMORY_REDUCE_CONSTANT_WITH_INPUT_INITIALIZER-constant.html","kind":19,"packageRank":0,"desc":"","enclosedBy":{"name":"ailia_tokenizer","kind":9,"href":"ailia_tokenizer/"}},{"name":"AILIA_MEMORY_REDUCE_INTERSTAGE","qualifiedName":"ailia_tokenizer.AILIA_MEMORY_REDUCE_INTERSTAGE","href":"ailia_tokenizer/AILIA_MEMORY_REDUCE_INTERSTAGE-constant.html","kind":19,"packageRank":0,"desc":"","enclosedBy":{"name":"ailia_tokenizer","kind":9,"href":"ailia_tokenizer/"}},{"name":"AILIA_MEMORY_REUSE_INTERSTAGE","qualifiedName":"ailia_tokenizer.AILIA_MEMORY_REUSE_INTERSTAGE","href":"ailia_tokenizer/AILIA_MEMORY_REUSE_INTERSTAGE-constant.html","kind":19,"packageRank":0,"desc":"","enclosedBy":{"name":"ailia_tokenizer","kind":9,"href":"ailia_tokenizer/"}},{"name":"AILIA_MULTITHREAD_AUTO","qualifiedName":"ailia_tokenizer.AILIA_MULTITHREAD_AUTO","href":"ailia_tokenizer/AILIA_MULTITHREAD_AUTO-constant.html","kind":19,"packageRank":0,"desc":"","enclosedBy":{"name":"ailia_tokenizer","kind":9,"href":"ailia_tokenizer/"}},{"name":"AILIA_PROFILE_AVERAGE","qualifiedName":"ailia_tokenizer.AILIA_PROFILE_AVERAGE","href":"ailia_tokenizer/AILIA_PROFILE_AVERAGE-constant.html","kind":19,"packageRank":0,"desc":"","enclosedBy":{"name":"ailia_tokenizer","kind":9,"href":"ailia_tokenizer/"}},{"name":"AILIA_PROFILE_DISABLE","qualifiedName":"ailia_tokenizer.AILIA_PROFILE_DISABLE","href":"ailia_tokenizer/AILIA_PROFILE_DISABLE-constant.html","kind":19,"packageRank":0,"desc":"","enclosedBy":{"name":"ailia_tokenizer","kind":9,"href":"ailia_tokenizer/"}},{"name":"AILIA_SHAPE_VERSION","qualifiedName":"ailia_tokenizer.AILIA_SHAPE_VERSION","href":"ailia_tokenizer/AILIA_SHAPE_VERSION-constant.html","kind":19,"packageRank":0,"desc":"","enclosedBy":{"name":"ailia_tokenizer","kind":9,"href":"ailia_tokenizer/"}},{"name":"AILIA_STATUS_BROKEN","qualifiedName":"ailia_tokenizer.AILIA_STATUS_BROKEN","href":"ailia_tokenizer/AILIA_STATUS_BROKEN-constant.html","kind":19,"packageRank":0,"desc":"","enclosedBy":{"name":"ailia_tokenizer","kind":9,"href":"ailia_tokenizer/"}},{"name":"AILIA_STATUS_DATA_HIDDEN","qualifiedName":"ailia_tokenizer.AILIA_STATUS_DATA_HIDDEN","href":"ailia_tokenizer/AILIA_STATUS_DATA_HIDDEN-constant.html","kind":19,"packageRank":0,"desc":"","enclosedBy":{"name":"ailia_tokenizer","kind":9,"href":"ailia_tokenizer/"}},{"name":"AILIA_STATUS_DATA_REMOVED","qualifiedName":"ailia_tokenizer.AILIA_STATUS_DATA_REMOVED","href":"ailia_tokenizer/AILIA_STATUS_DATA_REMOVED-constant.html","kind":19,"packageRank":0,"desc":"","enclosedBy":{"name":"ailia_tokenizer","kind":9,"href":"ailia_tokenizer/"}},{"name":"AILIA_STATUS_ERROR_FILE_API","qualifiedName":"ailia_tokenizer.AILIA_STATUS_ERROR_FILE_API","href":"ailia_tokenizer/AILIA_STATUS_ERROR_FILE_API-constant.html","kind":19,"packageRank":0,"desc":"","enclosedBy":{"name":"ailia_tokenizer","kind":9,"href":"ailia_tokenizer/"}},{"name":"AILIA_STATUS_EXPIRED","qualifiedName":"ailia_tokenizer.AILIA_STATUS_EXPIRED","href":"ailia_tokenizer/AILIA_STATUS_EXPIRED-constant.html","kind":19,"packageRank":0,"desc":"","enclosedBy":{"name":"ailia_tokenizer","kind":9,"href":"ailia_tokenizer/"}},{"name":"AILIA_STATUS_GPU_ERROR","qualifiedName":"ailia_tokenizer.AILIA_STATUS_GPU_ERROR","href":"ailia_tokenizer/AILIA_STATUS_GPU_ERROR-constant.html","kind":19,"packageRank":0,"desc":"","enclosedBy":{"name":"ailia_tokenizer","kind":9,"href":"ailia_tokenizer/"}},{"name":"AILIA_STATUS_GPU_UNSUPPORT_LAYER","qualifiedName":"ailia_tokenizer.AILIA_STATUS_GPU_UNSUPPORT_LAYER","href":"ailia_tokenizer/AILIA_STATUS_GPU_UNSUPPORT_LAYER-constant.html","kind":19,"packageRank":0,"desc":"","enclosedBy":{"name":"ailia_tokenizer","kind":9,"href":"ailia_tokenizer/"}},{"name":"AILIA_STATUS_INVALID_ARGUMENT","qualifiedName":"ailia_tokenizer.AILIA_STATUS_INVALID_ARGUMENT","href":"ailia_tokenizer/AILIA_STATUS_INVALID_ARGUMENT-constant.html","kind":19,"packageRank":0,"desc":"","enclosedBy":{"name":"ailia_tokenizer","kind":9,"href":"ailia_tokenizer/"}},{"name":"AILIA_STATUS_INVALID_LAYER","qualifiedName":"ailia_tokenizer.AILIA_STATUS_INVALID_LAYER","href":"ailia_tokenizer/AILIA_STATUS_INVALID_LAYER-constant.html","kind":19,"packageRank":0,"desc":"","enclosedBy":{"name":"ailia_tokenizer","kind":9,"href":"ailia_tokenizer/"}},{"name":"AILIA_STATUS_INVALID_PARAMINFO","qualifiedName":"ailia_tokenizer.AILIA_STATUS_INVALID_PARAMINFO","href":"ailia_tokenizer/AILIA_STATUS_INVALID_PARAMINFO-constant.html","kind":19,"packageRank":0,"desc":"","enclosedBy":{"name":"ailia_tokenizer","kind":9,"href":"ailia_tokenizer/"}},{"name":"AILIA_STATUS_INVALID_STATE","qualifiedName":"ailia_tokenizer.AILIA_STATUS_INVALID_STATE","href":"ailia_tokenizer/AILIA_STATUS_INVALID_STATE-constant.html","kind":19,"packageRank":0,"desc":"","enclosedBy":{"name":"ailia_tokenizer","kind":9,"href":"ailia_tokenizer/"}},{"name":"AILIA_STATUS_INVALID_VERSION","qualifiedName":"ailia_tokenizer.AILIA_STATUS_INVALID_VERSION","href":"ailia_tokenizer/AILIA_STATUS_INVALID_VERSION-constant.html","kind":19,"packageRank":0,"desc":"","enclosedBy":{"name":"ailia_tokenizer","kind":9,"href":"ailia_tokenizer/"}},{"name":"AILIA_STATUS_LICENSE_BROKEN","qualifiedName":"ailia_tokenizer.AILIA_STATUS_LICENSE_BROKEN","href":"ailia_tokenizer/AILIA_STATUS_LICENSE_BROKEN-constant.html","kind":19,"packageRank":0,"desc":"","enclosedBy":{"name":"ailia_tokenizer","kind":9,"href":"ailia_tokenizer/"}},{"name":"AILIA_STATUS_LICENSE_EXPIRED","qualifiedName":"ailia_tokenizer.AILIA_STATUS_LICENSE_EXPIRED","href":"ailia_tokenizer/AILIA_STATUS_LICENSE_EXPIRED-constant.html","kind":19,"packageRank":0,"desc":"","enclosedBy":{"name":"ailia_tokenizer","kind":9,"href":"ailia_tokenizer/"}},{"name":"AILIA_STATUS_LICENSE_NOT_FOUND","qualifiedName":"ailia_tokenizer.AILIA_STATUS_LICENSE_NOT_FOUND","href":"ailia_tokenizer/AILIA_STATUS_LICENSE_NOT_FOUND-constant.html","kind":19,"packageRank":0,"desc":"","enclosedBy":{"name":"ailia_tokenizer","kind":9,"href":"ailia_tokenizer/"}},{"name":"AILIA_STATUS_MEMORY_INSUFFICIENT","qualifiedName":"ailia_tokenizer.AILIA_STATUS_MEMORY_INSUFFICIENT","href":"ailia_tokenizer/AILIA_STATUS_MEMORY_INSUFFICIENT-constant.html","kind":19,"packageRank":0,"desc":"","enclosedBy":{"name":"ailia_tokenizer","kind":9,"href":"ailia_tokenizer/"}},{"name":"AILIA_STATUS_NDIMENSION_SHAPE","qualifiedName":"ailia_tokenizer.AILIA_STATUS_NDIMENSION_SHAPE","href":"ailia_tokenizer/AILIA_STATUS_NDIMENSION_SHAPE-constant.html","kind":19,"packageRank":0,"desc":"","enclosedBy":{"name":"ailia_tokenizer","kind":9,"href":"ailia_tokenizer/"}},{"name":"AILIA_STATUS_NOT_FOUND","qualifiedName":"ailia_tokenizer.AILIA_STATUS_NOT_FOUND","href":"ailia_tokenizer/AILIA_STATUS_NOT_FOUND-constant.html","kind":19,"packageRank":0,"desc":"","enclosedBy":{"name":"ailia_tokenizer","kind":9,"href":"ailia_tokenizer/"}},{"name":"AILIA_STATUS_OTHER_ERROR","qualifiedName":"ailia_tokenizer.AILIA_STATUS_OTHER_ERROR","href":"ailia_tokenizer/AILIA_STATUS_OTHER_ERROR-constant.html","kind":19,"packageRank":0,"desc":"","enclosedBy":{"name":"ailia_tokenizer","kind":9,"href":"ailia_tokenizer/"}},{"name":"AILIA_STATUS_PERMISSION_DENIED","qualifiedName":"ailia_tokenizer.AILIA_STATUS_PERMISSION_DENIED","href":"ailia_tokenizer/AILIA_STATUS_PERMISSION_DENIED-constant.html","kind":19,"packageRank":0,"desc":"","enclosedBy":{"name":"ailia_tokenizer","kind":9,"href":"ailia_tokenizer/"}},{"name":"AILIA_STATUS_SUCCESS","qualifiedName":"ailia_tokenizer.AILIA_STATUS_SUCCESS","href":"ailia_tokenizer/AILIA_STATUS_SUCCESS-constant.html","kind":19,"packageRank":0,"desc":"","enclosedBy":{"name":"ailia_tokenizer","kind":9,"href":"ailia_tokenizer/"}},{"name":"AILIA_STATUS_THREAD_ERROR","qualifiedName":"ailia_tokenizer.AILIA_STATUS_THREAD_ERROR","href":"ailia_tokenizer/AILIA_STATUS_THREAD_ERROR-constant.html","kind":19,"packageRank":0,"desc":"","enclosedBy":{"name":"ailia_tokenizer","kind":9,"href":"ailia_tokenizer/"}},{"name":"AILIA_STATUS_UNIMPLEMENTED","qualifiedName":"ailia_tokenizer.AILIA_STATUS_UNIMPLEMENTED","href":"ailia_tokenizer/AILIA_STATUS_UNIMPLEMENTED-constant.html","kind":19,"packageRank":0,"desc":"","enclosedBy":{"name":"ailia_tokenizer","kind":9,"href":"ailia_tokenizer/"}},{"name":"AILIA_STATUS_UNSETTLED_SHAPE","qualifiedName":"ailia_tokenizer.AILIA_STATUS_UNSETTLED_SHAPE","href":"ailia_tokenizer/AILIA_STATUS_UNSETTLED_SHAPE-constant.html","kind":19,"packageRank":0,"desc":"","enclosedBy":{"name":"ailia_tokenizer","kind":9,"href":"ailia_tokenizer/"}},{"name":"AILIA_STATUS_UNSUPPORT_NET","qualifiedName":"ailia_tokenizer.AILIA_STATUS_UNSUPPORT_NET","href":"ailia_tokenizer/AILIA_STATUS_UNSUPPORT_NET-constant.html","kind":19,"packageRank":0,"desc":"","enclosedBy":{"name":"ailia_tokenizer","kind":9,"href":"ailia_tokenizer/"}},{"name":"AILIA_TOKENIZER_FLAG_NONE","qualifiedName":"ailia_tokenizer.AILIA_TOKENIZER_FLAG_NONE","href":"ailia_tokenizer/AILIA_TOKENIZER_FLAG_NONE-constant.html","kind":19,"packageRank":0,"desc":"","enclosedBy":{"name":"ailia_tokenizer","kind":9,"href":"ailia_tokenizer/"}},{"name":"AILIA_TOKENIZER_FLAG_UTF8_SAFE","qualifiedName":"ailia_tokenizer.AILIA_TOKENIZER_FLAG_UTF8_SAFE","href":"ailia_tokenizer/AILIA_TOKENIZER_FLAG_UTF8_SAFE-constant.html","kind":19,"packageRank":0,"desc":"","enclosedBy":{"name":"ailia_tokenizer","kind":9,"href":"ailia_tokenizer/"}},{"name":"AILIA_TOKENIZER_TYPE_BERT","qualifiedName":"ailia_tokenizer.AILIA_TOKENIZER_TYPE_BERT","href":"ailia_tokenizer/AILIA_TOKENIZER_TYPE_BERT-constant.html","kind":19,"packageRank":0,"desc":"","enclosedBy":{"name":"ailia_tokenizer","kind":9,"href":"ailia_tokenizer/"}},{"name":"AILIA_TOKENIZER_TYPE_BERT_JAPANESE_CHARACTER","qualifiedName":"ailia_tokenizer.AILIA_TOKENIZER_TYPE_BERT_JAPANESE_CHARACTER","href":"ailia_tokenizer/AILIA_TOKENIZER_TYPE_BERT_JAPANESE_CHARACTER-constant.html","kind":19,"packageRank":0,"desc":"","enclosedBy":{"name":"ailia_tokenizer","kind":9,"href":"ailia_tokenizer/"}},{"name":"AILIA_TOKENIZER_TYPE_BERT_JAPANESE_WORDPIECE","qualifiedName":"ailia_tokenizer.AILIA_TOKENIZER_TYPE_BERT_JAPANESE_WORDPIECE","href":"ailia_tokenizer/AILIA_TOKENIZER_TYPE_BERT_JAPANESE_WORDPIECE-constant.html","kind":19,"packageRank":0,"desc":"","enclosedBy":{"name":"ailia_tokenizer","kind":9,"href":"ailia_tokenizer/"}},{"name":"AILIA_TOKENIZER_TYPE_CLIP","qualifiedName":"ailia_tokenizer.AILIA_TOKENIZER_TYPE_CLIP","href":"ailia_tokenizer/AILIA_TOKENIZER_TYPE_CLIP-constant.html","kind":19,"packageRank":0,"desc":"","enclosedBy":{"name":"ailia_tokenizer","kind":9,"href":"ailia_tokenizer/"}},{"name":"AILIA_TOKENIZER_TYPE_GEMMA","qualifiedName":"ailia_tokenizer.AILIA_TOKENIZER_TYPE_GEMMA","href":"ailia_tokenizer/AILIA_TOKENIZER_TYPE_GEMMA-constant.html","kind":19,"packageRank":0,"desc":"","enclosedBy":{"name":"ailia_tokenizer","kind":9,"href":"ailia_tokenizer/"}},{"name":"AILIA_TOKENIZER_TYPE_GPT2","qualifiedName":"ailia_tokenizer.AILIA_TOKENIZER_TYPE_GPT2","href":"ailia_tokenizer/AILIA_TOKENIZER_TYPE_GPT2-constant.html","kind":19,"packageRank":0,"desc":"","enclosedBy":{"name":"ailia_tokenizer","kind":9,"href":"ailia_tokenizer/"}},{"name":"AILIA_TOKENIZER_TYPE_LLAMA","qualifiedName":"ailia_tokenizer.AILIA_TOKENIZER_TYPE_LLAMA","href":"ailia_tokenizer/AILIA_TOKENIZER_TYPE_LLAMA-constant.html","kind":19,"packageRank":0,"desc":"","enclosedBy":{"name":"ailia_tokenizer","kind":9,"href":"ailia_tokenizer/"}},{"name":"AILIA_TOKENIZER_TYPE_MARIAN","qualifiedName":"ailia_tokenizer.AILIA_TOKENIZER_TYPE_MARIAN","href":"ailia_tokenizer/AILIA_TOKENIZER_TYPE_MARIAN-constant.html","kind":19,"packageRank":0,"desc":"","enclosedBy":{"name":"ailia_tokenizer","kind":9,"href":"ailia_tokenizer/"}},{"name":"AILIA_TOKENIZER_TYPE_ROBERTA","qualifiedName":"ailia_tokenizer.AILIA_TOKENIZER_TYPE_ROBERTA","href":"ailia_tokenizer/AILIA_TOKENIZER_TYPE_ROBERTA-constant.html","kind":19,"packageRank":0,"desc":"","enclosedBy":{"name":"ailia_tokenizer","kind":9,"href":"ailia_tokenizer/"}},{"name":"AILIA_TOKENIZER_TYPE_T5","qualifiedName":"ailia_tokenizer.AILIA_TOKENIZER_TYPE_T5","href":"ailia_tokenizer/AILIA_TOKENIZER_TYPE_T5-constant.html","kind":19,"packageRank":0,"desc":"","enclosedBy":{"name":"ailia_tokenizer","kind":9,"href":"ailia_tokenizer/"}},{"name":"AILIA_TOKENIZER_TYPE_WHISPER","qualifiedName":"ailia_tokenizer.AILIA_TOKENIZER_TYPE_WHISPER","href":"ailia_tokenizer/AILIA_TOKENIZER_TYPE_WHISPER-constant.html","kind":19,"packageRank":0,"desc":"","enclosedBy":{"name":"ailia_tokenizer","kind":9,"href":"ailia_tokenizer/"}},{"name":"AILIA_TOKENIZER_TYPE_XLM_ROBERTA","qualifiedName":"ailia_tokenizer.AILIA_TOKENIZER_TYPE_XLM_ROBERTA","href":"ailia_tokenizer/AILIA_TOKENIZER_TYPE_XLM_ROBERTA-constant.html","kind":19,"packageRank":0,"desc":"","enclosedBy":{"name":"ailia_tokenizer","kind":9,"href":"ailia_tokenizer/"}},{"name":"AILIA_USER_API_FAILED","qualifiedName":"ailia_tokenizer.AILIA_USER_API_FAILED","href":"ailia_tokenizer/AILIA_USER_API_FAILED-constant.html","kind":19,"packageRank":0,"desc":"","enclosedBy":{"name":"ailia_tokenizer","kind":9,"href":"ailia_tokenizer/"}},{"name":"AILIA_USER_API_FCLOSE","qualifiedName":"ailia_tokenizer.AILIA_USER_API_FCLOSE","href":"ailia_tokenizer/AILIA_USER_API_FCLOSE.html","kind":21,"packageRank":0,"desc":"~japanese\n@brief ファイルを閉じます\n@param void *  ユーザ定義ファイルポインタ\n@return\n成功した場合、 \\ref AILIA_USER_API_SUCCESS を返す。\n失敗した場合、 \\ref AILIA_USER_API_FAILED を返す。","enclosedBy":{"name":"ailia_tokenizer","kind":9,"href":"ailia_tokenizer/"}},{"name":"AILIA_USER_API_FCLOSEFunction","qualifiedName":"ailia_tokenizer.AILIA_USER_API_FCLOSEFunction","href":"ailia_tokenizer/AILIA_USER_API_FCLOSEFunction.html","kind":21,"packageRank":0,"desc":"","enclosedBy":{"name":"ailia_tokenizer","kind":9,"href":"ailia_tokenizer/"}},{"name":"AILIA_USER_API_FOPEN","qualifiedName":"ailia_tokenizer.AILIA_USER_API_FOPEN","href":"ailia_tokenizer/AILIA_USER_API_FOPEN.html","kind":21,"packageRank":0,"desc":"~japanese\n@brief ファイルを開きます\n@param const void *   ailiaOpenStreamEx() もしくは ailiaOpenWeightEx() に与えたfopen_args\n@return\n成功した場合、ユーザ定義ファイルポインタを返す。\n失敗した場合、NULLを返す。","enclosedBy":{"name":"ailia_tokenizer","kind":9,"href":"ailia_tokenizer/"}},{"name":"AILIA_USER_API_FOPENFunction","qualifiedName":"ailia_tokenizer.AILIA_USER_API_FOPENFunction","href":"ailia_tokenizer/AILIA_USER_API_FOPENFunction.html","kind":21,"packageRank":0,"desc":"","enclosedBy":{"name":"ailia_tokenizer","kind":9,"href":"ailia_tokenizer/"}},{"name":"AILIA_USER_API_FREAD","qualifiedName":"ailia_tokenizer.AILIA_USER_API_FREAD","href":"ailia_tokenizer/AILIA_USER_API_FREAD.html","kind":21,"packageRank":0,"desc":"~japanese\n@brief ファイルからデータを読み込みます\n@param void *                     読み込みデータ格納先のポインタ\n@param  \\ref AILIA_FSIZE_RETURN_TYPE     読み込みデータのバイト長さ\n@param void *                     ユーザ定義ファイルポインタ\n@return\n成功した場合、 \\ref AILIA_USER_API_SUCCESS を返す。\n失敗した場合、 \\ref AILIA_USER_API_FAILED を返す。\n標準APIとは異なり、返値はAILIA_USER_API_*になりますのでご注意ください。","enclosedBy":{"name":"ailia_tokenizer","kind":9,"href":"ailia_tokenizer/"}},{"name":"AILIA_USER_API_FREADFunction","qualifiedName":"ailia_tokenizer.AILIA_USER_API_FREADFunction","href":"ailia_tokenizer/AILIA_USER_API_FREADFunction.html","kind":21,"packageRank":0,"desc":"","enclosedBy":{"name":"ailia_tokenizer","kind":9,"href":"ailia_tokenizer/"}},{"name":"AILIA_USER_API_FSEEK","qualifiedName":"ailia_tokenizer.AILIA_USER_API_FSEEK","href":"ailia_tokenizer/AILIA_USER_API_FSEEK.html","kind":21,"packageRank":0,"desc":"~japanese\n@brief ファイルをシークします\n@param void *                     ユーザ定義ファイルポインタ\n@param  \\ref AILIA_FSIZE_RETURN_TYPE     ファイル先頭からのオフセットバイト\n@return\n成功した場合、 \\ref AILIA_USER_API_SUCCESS を返す。\n失敗した場合、 \\ref AILIA_USER_API_FAILED を返す。","enclosedBy":{"name":"ailia_tokenizer","kind":9,"href":"ailia_tokenizer/"}},{"name":"AILIA_USER_API_FSEEKFunction","qualifiedName":"ailia_tokenizer.AILIA_USER_API_FSEEKFunction","href":"ailia_tokenizer/AILIA_USER_API_FSEEKFunction.html","kind":21,"packageRank":0,"desc":"","enclosedBy":{"name":"ailia_tokenizer","kind":9,"href":"ailia_tokenizer/"}},{"name":"AILIA_USER_API_FSIZE","qualifiedName":"ailia_tokenizer.AILIA_USER_API_FSIZE","href":"ailia_tokenizer/AILIA_USER_API_FSIZE.html","kind":21,"packageRank":0,"desc":"~japanese\n@brief ファイルのサイズを取得します\n@param void * ユーザ定義ファイルポインタ\n@return\n成功した場合、ファイルのサイズをバイト単位で返す。\n失敗した場合、-1を返す。","enclosedBy":{"name":"ailia_tokenizer","kind":9,"href":"ailia_tokenizer/"}},{"name":"AILIA_USER_API_FSIZEFunction","qualifiedName":"ailia_tokenizer.AILIA_USER_API_FSIZEFunction","href":"ailia_tokenizer/AILIA_USER_API_FSIZEFunction.html","kind":21,"packageRank":0,"desc":"","enclosedBy":{"name":"ailia_tokenizer","kind":9,"href":"ailia_tokenizer/"}},{"name":"AILIA_USER_API_FTELL","qualifiedName":"ailia_tokenizer.AILIA_USER_API_FTELL","href":"ailia_tokenizer/AILIA_USER_API_FTELL.html","kind":21,"packageRank":0,"desc":"~japanese\n@brief ファイルの現在位置を取得します\n@param void * ユーザ定義ファイルポインタ\n@return\n成功した場合、ファイルポインタの位置をバイト単位で返す。\n失敗した場合、-1を返す。","enclosedBy":{"name":"ailia_tokenizer","kind":9,"href":"ailia_tokenizer/"}},{"name":"AILIA_USER_API_FTELLFunction","qualifiedName":"ailia_tokenizer.AILIA_USER_API_FTELLFunction","href":"ailia_tokenizer/AILIA_USER_API_FTELLFunction.html","kind":21,"packageRank":0,"desc":"","enclosedBy":{"name":"ailia_tokenizer","kind":9,"href":"ailia_tokenizer/"}},{"name":"AILIA_USER_API_SUCCESS","qualifiedName":"ailia_tokenizer.AILIA_USER_API_SUCCESS","href":"ailia_tokenizer/AILIA_USER_API_SUCCESS-constant.html","kind":19,"packageRank":0,"desc":"","enclosedBy":{"name":"ailia_tokenizer","kind":9,"href":"ailia_tokenizer/"}},{"name":"DartAILIA_USER_API_FCLOSEFunction","qualifiedName":"ailia_tokenizer.DartAILIA_USER_API_FCLOSEFunction","href":"ailia_tokenizer/DartAILIA_USER_API_FCLOSEFunction.html","kind":21,"packageRank":0,"desc":"","enclosedBy":{"name":"ailia_tokenizer","kind":9,"href":"ailia_tokenizer/"}},{"name":"DartAILIA_USER_API_FREADFunction","qualifiedName":"ailia_tokenizer.DartAILIA_USER_API_FREADFunction","href":"ailia_tokenizer/DartAILIA_USER_API_FREADFunction.html","kind":21,"packageRank":0,"desc":"","enclosedBy":{"name":"ailia_tokenizer","kind":9,"href":"ailia_tokenizer/"}},{"name":"DartAILIA_USER_API_FSEEKFunction","qualifiedName":"ailia_tokenizer.DartAILIA_USER_API_FSEEKFunction","href":"ailia_tokenizer/DartAILIA_USER_API_FSEEKFunction.html","kind":21,"packageRank":0,"desc":"","enclosedBy":{"name":"ailia_tokenizer","kind":9,"href":"ailia_tokenizer/"}},{"name":"DartAILIA_USER_API_FSIZEFunction","qualifiedName":"ailia_tokenizer.DartAILIA_USER_API_FSIZEFunction","href":"ailia_tokenizer/DartAILIA_USER_API_FSIZEFunction.html","kind":21,"packageRank":0,"desc":"","enclosedBy":{"name":"ailia_tokenizer","kind":9,"href":"ailia_tokenizer/"}},{"name":"DartAILIA_USER_API_FTELLFunction","qualifiedName":"ailia_tokenizer.DartAILIA_USER_API_FTELLFunction","href":"ailia_tokenizer/DartAILIA_USER_API_FTELLFunction.html","kind":21,"packageRank":0,"desc":"","enclosedBy":{"name":"ailia_tokenizer","kind":9,"href":"ailia_tokenizer/"}},{"name":"NULL","qualifiedName":"ailia_tokenizer.NULL","href":"ailia_tokenizer/NULL-constant.html","kind":19,"packageRank":0,"desc":"","enclosedBy":{"name":"ailia_tokenizer","kind":9,"href":"ailia_tokenizer/"}},{"name":"USER_ADDR_NULL","qualifiedName":"ailia_tokenizer.USER_ADDR_NULL","href":"ailia_tokenizer/USER_ADDR_NULL-constant.html","kind":19,"packageRank":0,"desc":"","enclosedBy":{"name":"ailia_tokenizer","kind":9,"href":"ailia_tokenizer/"}},{"name":"ailiaFileCallback","qualifiedName":"ailia_tokenizer.ailiaFileCallback","href":"ailia_tokenizer/ailiaFileCallback.html","kind":21,"packageRank":0,"desc":"","enclosedBy":{"name":"ailia_tokenizer","kind":9,"href":"ailia_tokenizer/"}},{"name":"ailiaTokenizerFFI","qualifiedName":"ailia_tokenizer.ailiaTokenizerFFI","href":"ailia_tokenizer/ailiaTokenizerFFI-class.html","kind":3,"packageRank":0,"desc":"Written for the FFI article","enclosedBy":{"name":"ailia_tokenizer","kind":9,"href":"ailia_tokenizer/"}},{"name":"ailiaCopyBlobData","qualifiedName":"ailia_tokenizer.ailiaTokenizerFFI.ailiaCopyBlobData","href":"ailia_tokenizer/ailiaTokenizerFFI/ailiaCopyBlobData.html","kind":10,"overriddenDepth":0,"packageRank":0,"desc":"~japanese\n@brief 指定したBlob間でデータをコピーします","enclosedBy":{"name":"ailiaTokenizerFFI","kind":3,"href":"ailia_tokenizer/ailiaTokenizerFFI-class.html"}},{"name":"ailiaCreate","qualifiedName":"ailia_tokenizer.ailiaTokenizerFFI.ailiaCreate","href":"ailia_tokenizer/ailiaTokenizerFFI/ailiaCreate.html","kind":10,"overriddenDepth":0,"packageRank":0,"desc":"~japanese\n@brief ネットワークオブジェクトを作成します。\n@param net ネットワークオブジェクトポインタへのポインタ\n@param env_id 計算に利用する推論実行環境のID( ailiaGetEnvironment() で取得)  \\ref AILIA_ENVIRONMENT_ID_AUTO\nにした場合は自動で選択する\n@param num_thread スレッド数の上限(  \\ref AILIA_MULTITHREAD_AUTO  にした場合は自動で設定)\n@return\n成功した場合は \\ref AILIA_STATUS_SUCCESS 、そうでなければエラーコードを返す。\n@details\nネットワークオブジェクトを作成します。\n推論実行環境を自動にした場合はCPUモードになり、BLASが利用できる場合はBLASを利用します。\nなお、BLASを利用する場合num_threadは無視される場合があります。","enclosedBy":{"name":"ailiaTokenizerFFI","kind":3,"href":"ailia_tokenizer/ailiaTokenizerFFI-class.html"}},{"name":"ailiaDestroy","qualifiedName":"ailia_tokenizer.ailiaTokenizerFFI.ailiaDestroy","href":"ailia_tokenizer/ailiaTokenizerFFI/ailiaDestroy.html","kind":10,"overriddenDepth":0,"packageRank":0,"desc":"~japanese\n@brief ネットワークオブジェクトを破棄します。\n@param net ネットワークオブジェクトポインタ","enclosedBy":{"name":"ailiaTokenizerFFI","kind":3,"href":"ailia_tokenizer/ailiaTokenizerFFI-class.html"}},{"name":"ailiaDisableLayerFusion","qualifiedName":"ailia_tokenizer.ailiaTokenizerFFI.ailiaDisableLayerFusion","href":"ailia_tokenizer/ailiaTokenizerFFI/ailiaDisableLayerFusion.html","kind":10,"overriddenDepth":0,"packageRank":0,"desc":"~japanese\n@brief 推論時のレイヤー統合を無効化します\n@param net ネットワークオブジェクトポインタ\n@return\n成功した場合は \\ref AILIA_STATUS_SUCCESS 、そうでなければエラーコードを返す。\n@details\nレイヤー統合により取得できなくなるBlobを取得する必要がある場合などに用います。\nailiaCreate() の直後に指定する必要があります。ailiaOpenを呼び出した後は変更することができません。\nなお、レイヤー統合を無効化すると推論速度が低下する場合があります。","enclosedBy":{"name":"ailiaTokenizerFFI","kind":3,"href":"ailia_tokenizer/ailiaTokenizerFFI-class.html"}},{"name":"ailiaFinalize","qualifiedName":"ailia_tokenizer.ailiaTokenizerFFI.ailiaFinalize","href":"ailia_tokenizer/ailiaTokenizerFFI/ailiaFinalize.html","kind":10,"overriddenDepth":0,"packageRank":0,"desc":"~japanese\n@brief ailiaがグローバルに確保したGPUリソース等を解放します\n@return\n成功した場合は \\ref AILIA_STATUS_SUCCESS 、そうでなければエラーコードを返します。\n@details\nailiaCreate() で作成したインスタンス全てを ailiaDestroy() で解放した状態で呼び出す必要があります。\nそれ以外の状態で呼び出された場合 #ref AILIA_STATUS_INVALID_STATE を返します。\nWindows 環境の場合、DllMain 等からこの API を呼び出すとデッドロックする可能性があります。","enclosedBy":{"name":"ailiaTokenizerFFI","kind":3,"href":"ailia_tokenizer/ailiaTokenizerFFI-class.html"}},{"name":"ailiaFindBlobIndexByName","qualifiedName":"ailia_tokenizer.ailiaTokenizerFFI.ailiaFindBlobIndexByName","href":"ailia_tokenizer/ailiaTokenizerFFI/ailiaFindBlobIndexByName.html","kind":10,"overriddenDepth":0,"packageRank":0,"desc":"~japanese\n@brief 推論時の内部データ(Blob)のインデックスを名前で探し取得します。\n@param net ネットワークオブジェクトポインタ\n@param blob_idx blobのインデックス (0～ ailiaGetBlobCount() -1)\n@param name 検索するBlob名\n@return\n成功した場合は \\ref AILIA_STATUS_SUCCESS 、そうでなければエラーコードを返す。\n@details\nこのAPIはailiaOpenStreamXXX呼び出し後より利用可能です。\nなお、ailiaOpenStreamXXX呼び出し時は入出力Blobのみが検索可能です。中間Blobを検索する場合ailiaOpneWeightXXXを呼び出す必要があります。","enclosedBy":{"name":"ailiaTokenizerFFI","kind":3,"href":"ailia_tokenizer/ailiaTokenizerFFI-class.html"}},{"name":"ailiaFindBlobNameByIndex","qualifiedName":"ailia_tokenizer.ailiaTokenizerFFI.ailiaFindBlobNameByIndex","href":"ailia_tokenizer/ailiaTokenizerFFI/ailiaFindBlobNameByIndex.html","kind":10,"overriddenDepth":0,"packageRank":0,"desc":"~japanese\n@brief 推論時の内部データ(Blob)の名前をインデックスで探し取得します。\n@param net ネットワークオブジェクトポインタ\n@param buffer Blob名の出力先バッファ\n@param buffer_size バッファのサイズ(終端null文字分を含む)\n@param blob_idx 検索するblobのインデックス\n@return\n成功した場合は \\ref AILIA_STATUS_SUCCESS 、そうでなければエラーコードを返す。\n@details\nこのAPIはailiaOpenStreamXXX呼び出し後より利用可能です。\nなお、ailiaOpenStreamXXX呼び出し時は入出力Blobのみが検索可能です。中間Blobを検索する場合ailiaOpneWeightXXXを呼び出す必要があります。","enclosedBy":{"name":"ailiaTokenizerFFI","kind":3,"href":"ailia_tokenizer/ailiaTokenizerFFI-class.html"}},{"name":"ailiaGetBlobCount","qualifiedName":"ailia_tokenizer.ailiaTokenizerFFI.ailiaGetBlobCount","href":"ailia_tokenizer/ailiaTokenizerFFI/ailiaGetBlobCount.html","kind":10,"overriddenDepth":0,"packageRank":0,"desc":"~japanese\n@brief 推論時の内部データ(Blob)の数を取得します。\n@param net ネットワークオブジェクトポインタ\n@param blob_count blobの数の格納先\n@return\n成功した場合は \\ref AILIA_STATUS_SUCCESS 、そうでなければエラーコードを返す。\n@details\nこのAPIはailiaOpenStreamXXX呼び出し後より利用可能です。\nなお、ailiaOpenStreamXXX呼び出し時は入出力Blobのみが列挙され、ailiaOpneWeightXXX呼び出し時に中間Blobの列挙が行われます。\nそのためailiaOpenStreamXXX呼び出し直後とailiaOpneWeightXXX呼び出し直後で返答する数が変わる場合があります。","enclosedBy":{"name":"ailiaTokenizerFFI","kind":3,"href":"ailia_tokenizer/ailiaTokenizerFFI-class.html"}},{"name":"ailiaGetBlobData","qualifiedName":"ailia_tokenizer.ailiaTokenizerFFI.ailiaGetBlobData","href":"ailia_tokenizer/ailiaTokenizerFFI/ailiaGetBlobData.html","kind":10,"overriddenDepth":0,"packageRank":0,"desc":"~japanese\n@brief 推論時の内部データ(Blob)を取得します。\n@param net ネットワークオブジェクトポインタ\n@param dest 推論結果の書き出し先バッファにX,Y,Z,Wの順でnumeric型で格納\n@param dest_size 推論結果の書き出し先バッファのbyte数\n@param blob_idx blobのインデックス (0～ ailiaGetBlobCount() -1)\n@return\n成功した場合は \\ref AILIA_STATUS_SUCCESS 、そうでなければエラーコードを返す。\n@details\nailiaPredict() または ailiaUpdate() を一度も実行していない場合は \\ref AILIA_STATUS_INVALID_STATE が返ります。","enclosedBy":{"name":"ailiaTokenizerFFI","kind":3,"href":"ailia_tokenizer/ailiaTokenizerFFI-class.html"}},{"name":"ailiaGetBlobDataType","qualifiedName":"ailia_tokenizer.ailiaTokenizerFFI.ailiaGetBlobDataType","href":"ailia_tokenizer/ailiaTokenizerFFI/ailiaGetBlobDataType.html","kind":10,"overriddenDepth":0,"packageRank":0,"desc":"~japanese\n@brief 推論時の内部データ(Blob)の型を取得します。\n@param net ネットワークオブジェクトポインタ\n@param type データ型の書き出し先バッファ。値は AILIA_DATATYPE_XXX で定義されています。\n@param blob_idx blobのインデックス (0～ ailiaGetBlobCount() -1)\n@return\n成功した場合は \\ref AILIA_STATUS_SUCCESS 、そうでなければエラーコードを返す。\n@details\nこのAPIはailiaOpenWeighXXX呼び出し後より利用可能です。","enclosedBy":{"name":"ailiaTokenizerFFI","kind":3,"href":"ailia_tokenizer/ailiaTokenizerFFI-class.html"}},{"name":"ailiaGetBlobDim","qualifiedName":"ailia_tokenizer.ailiaTokenizerFFI.ailiaGetBlobDim","href":"ailia_tokenizer/ailiaTokenizerFFI/ailiaGetBlobDim.html","kind":10,"overriddenDepth":0,"packageRank":0,"desc":"~japanese\n@brief 推論時の内部データ(Blob)の次元を取得します。\n@param net ネットワークオブジェクトポインタ\n@param dim blobの次元の格納先\n@param blob_idx blobのインデックス (0～ ailiaGetBlobCount() -1)\n@return\n成功した場合は \\ref AILIA_STATUS_SUCCESS 、それ以外のエラーの場合はエラーコードを返す。\n@details\nこのAPIはailiaOpenWeighXXX呼び出し後より利用可能です。","enclosedBy":{"name":"ailiaTokenizerFFI","kind":3,"href":"ailia_tokenizer/ailiaTokenizerFFI-class.html"}},{"name":"ailiaGetBlobIndexByInputIndex","qualifiedName":"ailia_tokenizer.ailiaTokenizerFFI.ailiaGetBlobIndexByInputIndex","href":"ailia_tokenizer/ailiaTokenizerFFI/ailiaGetBlobIndexByInputIndex.html","kind":10,"overriddenDepth":0,"packageRank":0,"desc":"~japanese\n@brief 入力データ(Blob)のインデックスを取得します\n@param net ネットワークオブジェクトポインタ\n@param blob_idx blobのインデックス(0～ ailiaGetBlobCount() -1)\n@param input_blob_idx 入力blob内でのインデックス(0～ ailiaGetInputBlobCount() -1)\n@return\n成功した場合は \\ref AILIA_STATUS_SUCCESS 、そうでなければエラーコードを返す。\n@details\nこのAPIはailiaOpenStreamXXX呼び出し後より利用可能です。\nなお、ailiaOpenStreamXXX呼び出し時に列挙されたinput_blob_idx及びblob_idxは保持されるためailiaOpneWeightXXX呼び出し後も同じ値が返ることが保証されます。","enclosedBy":{"name":"ailiaTokenizerFFI","kind":3,"href":"ailia_tokenizer/ailiaTokenizerFFI-class.html"}},{"name":"ailiaGetBlobIndexByOutputIndex","qualifiedName":"ailia_tokenizer.ailiaTokenizerFFI.ailiaGetBlobIndexByOutputIndex","href":"ailia_tokenizer/ailiaTokenizerFFI/ailiaGetBlobIndexByOutputIndex.html","kind":10,"overriddenDepth":0,"packageRank":0,"desc":"~japanese\n@brief 出力データ(Blob)のインデックスを取得します\n@param net ネットワークオブジェクトポインタ\n@param blob_idx blobのインデックス(0～ ailiaGetBlobCount() -1)\n@param output_blob_idx 出力blob内でのインデックス(0～ ailiaGetOutputBlobCount() -1)\n@return\n成功した場合は \\ref AILIA_STATUS_SUCCESS 、そうでなければエラーコードを返す。\n@details\nこのAPIはailiaOpenStreamXXX呼び出し後より利用可能です。","enclosedBy":{"name":"ailiaTokenizerFFI","kind":3,"href":"ailia_tokenizer/ailiaTokenizerFFI-class.html"}},{"name":"ailiaGetBlobNameLengthByIndex","qualifiedName":"ailia_tokenizer.ailiaTokenizerFFI.ailiaGetBlobNameLengthByIndex","href":"ailia_tokenizer/ailiaTokenizerFFI/ailiaGetBlobNameLengthByIndex.html","kind":10,"overriddenDepth":0,"packageRank":0,"desc":"~japanese\n@brief 内部データ(Blob)の名前の出力に必要なバッファのサイズを取得します。\n@param net ネットワークオブジェクトポインタ\n@param blob_idx blobのインデックス (0～ ailiaGetBlobCount() -1)\n@param buffer_size Blob名の出力に必要なバッファのサイズ(終端null文字分を含む)\n@return\n成功した場合は \\ref AILIA_STATUS_SUCCESS 、そうでなければエラーコードを返す。\n@details\nこのAPIはailiaOpenStreamXXX呼び出し後より利用可能です。\nなお、ailiaOpenStreamXXX呼び出し時は入出力Blobのみが検索可能です。中間Blobを検索する場合ailiaOpneWeightXXXを呼び出す必要があります。","enclosedBy":{"name":"ailiaTokenizerFFI","kind":3,"href":"ailia_tokenizer/ailiaTokenizerFFI-class.html"}},{"name":"ailiaGetBlobShape","qualifiedName":"ailia_tokenizer.ailiaTokenizerFFI.ailiaGetBlobShape","href":"ailia_tokenizer/ailiaTokenizerFFI/ailiaGetBlobShape.html","kind":10,"overriddenDepth":0,"packageRank":0,"desc":"~japanese\n@brief 推論時の内部データ(Blob)の形状を取得します。\n@param net ネットワークオブジェクトポインタ\n@param shape データの形状情報の格納先\n@param blob_idx blobのインデックス (0～ ailiaGetBlobCount() -1)\n@param version AILIA_SHAPE_VERSION\n@return\n成功した場合は \\ref AILIA_STATUS_SUCCESS 、5次元以上の場合 \\ref AILIA_STATUS_NDIMENSION_SHAPE 、\nそれ以外のエラーの場合はエラーコードを返す。\n@details\n形状が5次元以上の場合は ailiaGetBlobDim() 、 ailiaGetBlobShapeND() を利用してください。\nこのAPIはailiaOpenWeighXXX呼び出し後より利用可能です。","enclosedBy":{"name":"ailiaTokenizerFFI","kind":3,"href":"ailia_tokenizer/ailiaTokenizerFFI-class.html"}},{"name":"ailiaGetBlobShapeND","qualifiedName":"ailia_tokenizer.ailiaTokenizerFFI.ailiaGetBlobShapeND","href":"ailia_tokenizer/ailiaTokenizerFFI/ailiaGetBlobShapeND.html","kind":10,"overriddenDepth":0,"packageRank":0,"desc":"~japanese\n@brief 推論時の内部データ(Blob)の形状を取得します。\n@param net ネットワークオブジェクトポインタ\n@param shape blobの各次元の大きさの格納先配列(dim-1, dim-2, ... ,1, 0順で格納)\n@param dim shapeの次元\n@param blob_idx blobのインデックス (0～ ailiaGetBlobCount() -1)\n@return\n成功した場合は \\ref AILIA_STATUS_SUCCESS 、それ以外のエラーの場合はエラーコードを返す。\n@details\nこのAPIはailiaOpenWeighXXX呼び出し後より利用可能です。","enclosedBy":{"name":"ailiaTokenizerFFI","kind":3,"href":"ailia_tokenizer/ailiaTokenizerFFI-class.html"}},{"name":"ailiaGetEnvironment","qualifiedName":"ailia_tokenizer.ailiaTokenizerFFI.ailiaGetEnvironment","href":"ailia_tokenizer/ailiaTokenizerFFI/ailiaGetEnvironment.html","kind":10,"overriddenDepth":0,"packageRank":0,"desc":"~japanese\n@brief 計算環境の一覧を取得します\n@param env 計算環境情報の格納先(AILIANetworkインスタンスを破棄するまで有効)\n@param env_idx 計算環境情報のインデックス(0～ ailiaGetEnvironmentCount() -1)\n@param version AILIA_ENVIRONMENT_VERSION\n@return\n成功した場合は \\ref AILIA_STATUS_SUCCESS 、そうでなければエラーコードを返す。","enclosedBy":{"name":"ailiaTokenizerFFI","kind":3,"href":"ailia_tokenizer/ailiaTokenizerFFI-class.html"}},{"name":"ailiaGetEnvironmentCount","qualifiedName":"ailia_tokenizer.ailiaTokenizerFFI.ailiaGetEnvironmentCount","href":"ailia_tokenizer/ailiaTokenizerFFI/ailiaGetEnvironmentCount.html","kind":10,"overriddenDepth":0,"packageRank":0,"desc":"~japanese\n@brief 利用可能な計算環境(CPU, GPU)の数を取得します\n@param env_count 計算環境情報の数の格納先\n@return\n成功した場合は \\ref AILIA_STATUS_SUCCESS 、そうでなければエラーコードを返す。","enclosedBy":{"name":"ailiaTokenizerFFI","kind":3,"href":"ailia_tokenizer/ailiaTokenizerFFI-class.html"}},{"name":"ailiaGetErrorDetail","qualifiedName":"ailia_tokenizer.ailiaTokenizerFFI.ailiaGetErrorDetail","href":"ailia_tokenizer/ailiaTokenizerFFI/ailiaGetErrorDetail.html","kind":10,"overriddenDepth":0,"packageRank":0,"desc":"~japanese\n@brief エラーの詳細を返します\n@param net   ネットワークオブジェクトポインタ\n@return\nエラー詳細\n@details\n返値は解放する必要はありません。\n文字列の有効期間は次にailiaのAPIを呼ぶまでです。\nモデルが暗号化されている場合は空文字を返します。","enclosedBy":{"name":"ailiaTokenizerFFI","kind":3,"href":"ailia_tokenizer/ailiaTokenizerFFI-class.html"}},{"name":"ailiaGetInputBlobCount","qualifiedName":"ailia_tokenizer.ailiaTokenizerFFI.ailiaGetInputBlobCount","href":"ailia_tokenizer/ailiaTokenizerFFI/ailiaGetInputBlobCount.html","kind":10,"overriddenDepth":0,"packageRank":0,"desc":"~japanese\n@brief 入力データ(Blob)の数を取得します。\n@param net ネットワークオブジェクトポインタ\n@param input_blob_count 入力blobの数の格納先\n@return\n成功した場合は \\ref AILIA_STATUS_SUCCESS 、そうでなければエラーコードを返す。\n@details\nこのAPIはailiaOpenStreamXXX呼び出し後より利用可能です。\nなお、入力Blobの列挙はailiaOpenStreamXXX呼び出し時に行われますが変更可能な重み(input付きinitialzier)の列挙はailiaOpneWeightXXX呼び出し時に行われます。\nそのためailiaOpenStreamXXX呼び出し直後とailiaOpneWeightXXX呼び出し直後で返答する数が変わる場合があります。","enclosedBy":{"name":"ailiaTokenizerFFI","kind":3,"href":"ailia_tokenizer/ailiaTokenizerFFI-class.html"}},{"name":"ailiaGetInputDim","qualifiedName":"ailia_tokenizer.ailiaTokenizerFFI.ailiaGetInputDim","href":"ailia_tokenizer/ailiaTokenizerFFI/ailiaGetInputDim.html","kind":10,"overriddenDepth":0,"packageRank":0,"desc":"~japanese\n@brief 推論時の入力データの次元を取得します。\n@param net ネットワークオブジェクトポインタ\n@param dim 入力データの次元の格納先\n@return\n成功した場合は \\ref AILIA_STATUS_SUCCESS 、それ以外のエラーの場合はエラーコードを返す。\n@details\nこのAPIはailiaOpenWeighXXX呼び出し後より利用可能です。","enclosedBy":{"name":"ailiaTokenizerFFI","kind":3,"href":"ailia_tokenizer/ailiaTokenizerFFI-class.html"}},{"name":"ailiaGetInputShape","qualifiedName":"ailia_tokenizer.ailiaTokenizerFFI.ailiaGetInputShape","href":"ailia_tokenizer/ailiaTokenizerFFI/ailiaGetInputShape.html","kind":10,"overriddenDepth":0,"packageRank":0,"desc":"~japanese\n@brief 推論時の入力データの形状を取得します。\n@param net ネットワークオブジェクトポインタ\n@param shape 入力データの形状情報\n@param version AILIA_SHAPE_VERSION\n@return\n成功した場合は \\ref AILIA_STATUS_SUCCESS 、5次元以上の場合 \\ref AILIA_STATUS_NDIMENSION_SHAPE 、\n形状の一部が未確定の場合 \\ref AILIA_STATUS_UNSETTLED_SHAPE 、それ以外のエラーの場合はエラーコードを返す。\n@details\n形状が5次元以上の場合は ailiaGetInputDim() 、 ailiaGetInputShapeND() を利用してください。\n形状の一部が未確定の場合、該当する次元の値は0となり、それ以外の次元の値は有効な値が格納されます。\nこのAPIはailiaOpenWeighXXX呼び出し後より利用可能です。","enclosedBy":{"name":"ailiaTokenizerFFI","kind":3,"href":"ailia_tokenizer/ailiaTokenizerFFI-class.html"}},{"name":"ailiaGetInputShapeND","qualifiedName":"ailia_tokenizer.ailiaTokenizerFFI.ailiaGetInputShapeND","href":"ailia_tokenizer/ailiaTokenizerFFI/ailiaGetInputShapeND.html","kind":10,"overriddenDepth":0,"packageRank":0,"desc":"~japanese\n@brief 推論時の入力データの形状を取得します。\n@param net ネットワークオブジェクトポインタ\n@param shape 入力データの各次元の大きさの格納先配列(dim-1, dim-2, ... ,1, 0順で格納)\n@param dim shapeの次元\n@return\n成功した場合は \\ref AILIA_STATUS_SUCCESS 、形状の一部が未確定の場合 \\ref AILIA_STATUS_UNSETTLED_SHAPE 、\nそれ以外のエラーの場合はエラーコードを返す。\n@details\n形状の一部が未確定の場合、該当する次元の値は0となり、それ以外の次元の値は有効な値が格納されます。\nこのAPIはailiaOpenWeighXXX呼び出し後より利用可能です。","enclosedBy":{"name":"ailiaTokenizerFFI","kind":3,"href":"ailia_tokenizer/ailiaTokenizerFFI-class.html"}},{"name":"ailiaGetOutputBlobCount","qualifiedName":"ailia_tokenizer.ailiaTokenizerFFI.ailiaGetOutputBlobCount","href":"ailia_tokenizer/ailiaTokenizerFFI/ailiaGetOutputBlobCount.html","kind":10,"overriddenDepth":0,"packageRank":0,"desc":"~japanese\n@brief 出力データ(Blob)の数を取得します。\n@param net ネットワークオブジェクトポインタ\n@param output_blob_count 出力blobの数の格納先\n@return\n成功した場合は \\ref AILIA_STATUS_SUCCESS 、そうでなければエラーコードを返す。\n@details\nこのAPIはailiaOpenStreamXXX呼び出し後より利用可能です。","enclosedBy":{"name":"ailiaTokenizerFFI","kind":3,"href":"ailia_tokenizer/ailiaTokenizerFFI-class.html"}},{"name":"ailiaGetOutputDim","qualifiedName":"ailia_tokenizer.ailiaTokenizerFFI.ailiaGetOutputDim","href":"ailia_tokenizer/ailiaTokenizerFFI/ailiaGetOutputDim.html","kind":10,"overriddenDepth":0,"packageRank":0,"desc":"~japanese\n@brief 推論時の出力データの次元を取得します。\n@param net ネットワークオブジェクトポインタ\n@param dim 出力データの次元の格納先\n@return\n成功した場合は \\ref AILIA_STATUS_SUCCESS 、それ以外のエラーの場合はエラーコードを返す。\n@details\nこのAPIはailiaOpenWeighXXX呼び出し後より利用可能です。","enclosedBy":{"name":"ailiaTokenizerFFI","kind":3,"href":"ailia_tokenizer/ailiaTokenizerFFI-class.html"}},{"name":"ailiaGetOutputShape","qualifiedName":"ailia_tokenizer.ailiaTokenizerFFI.ailiaGetOutputShape","href":"ailia_tokenizer/ailiaTokenizerFFI/ailiaGetOutputShape.html","kind":10,"overriddenDepth":0,"packageRank":0,"desc":"~japanese\n@brief 推論時の出力データの形状を取得します。\n@param net ネットワークオブジェクトポインタ\n@param shape 出力データの形状情報\n@param version AILIA_SHAPE_VERSION\n@return\n成功した場合は \\ref AILIA_STATUS_SUCCESS 、5次元以上の場合 \\ref AILIA_STATUS_NDIMENSION_SHAPE 、\nそれ以外のエラーの場合エラーコードを返す。\n形状が5次元以上の場合は ailiaGetOutputDim() 、 ailiaGetOutputShapeND() を利用してください。\nこのAPIはailiaOpenWeighXXX呼び出し後より利用可能です。","enclosedBy":{"name":"ailiaTokenizerFFI","kind":3,"href":"ailia_tokenizer/ailiaTokenizerFFI-class.html"}},{"name":"ailiaGetOutputShapeND","qualifiedName":"ailia_tokenizer.ailiaTokenizerFFI.ailiaGetOutputShapeND","href":"ailia_tokenizer/ailiaTokenizerFFI/ailiaGetOutputShapeND.html","kind":10,"overriddenDepth":0,"packageRank":0,"desc":"~japanese\n@brief 推論時の出力データの形状を取得します。\n@param net ネットワークオブジェクトポインタ\n@param shape 出力データの各次元の大きさの格納先配列(dim-1, dim-2, ... ,1, 0順で格納)\n@param dim shapeの次元\n@return\n成功した場合は \\ref AILIA_STATUS_SUCCESS 、それ以外のエラーの場合はエラーコードを返す。\n@details\nこのAPIはailiaOpenWeighXXX呼び出し後より利用可能です。","enclosedBy":{"name":"ailiaTokenizerFFI","kind":3,"href":"ailia_tokenizer/ailiaTokenizerFFI-class.html"}},{"name":"ailiaGetSelectedEnvironment","qualifiedName":"ailia_tokenizer.ailiaTokenizerFFI.ailiaGetSelectedEnvironment","href":"ailia_tokenizer/ailiaTokenizerFFI/ailiaGetSelectedEnvironment.html","kind":10,"overriddenDepth":0,"packageRank":0,"desc":"~japanese\n@brief 選択された計算環境を取得します\n@param net ネットワークオブジェクトポインタ\n@param env 計算環境情報の格納先(AILIANetworkインスタンスを破棄するまで有効)\n@param version AILIA_ENVIRONMENT_VERSION\n@return\n成功した場合は \\ref AILIA_STATUS_SUCCESS 、そうでなければエラーコードを返す。","enclosedBy":{"name":"ailiaTokenizerFFI","kind":3,"href":"ailia_tokenizer/ailiaTokenizerFFI-class.html"}},{"name":"ailiaGetStatusString","qualifiedName":"ailia_tokenizer.ailiaTokenizerFFI.ailiaGetStatusString","href":"ailia_tokenizer/ailiaTokenizerFFI/ailiaGetStatusString.html","kind":10,"overriddenDepth":0,"packageRank":0,"desc":"~japanese\n@brief ステータスコードに対応する文字列を返します。\n@param status_code   ステータスコード\n@return\nステータスコードに対応する文字列。\n@details\n返値は解放する必要はありません。\n返された文字列は ailia のライブラリ(ailia.dll, libailia.so 等)をアンロードするまで有効です。\nAILIANetwork のインスタンスがある場合は ailiaGetErrorDetail() でエラーの詳細を取得できます。","enclosedBy":{"name":"ailiaTokenizerFFI","kind":3,"href":"ailia_tokenizer/ailiaTokenizerFFI-class.html"}},{"name":"ailiaGetSummaryLength","qualifiedName":"ailia_tokenizer.ailiaTokenizerFFI.ailiaGetSummaryLength","href":"ailia_tokenizer/ailiaTokenizerFFI/ailiaGetSummaryLength.html","kind":10,"overriddenDepth":0,"packageRank":0,"desc":"~japanese\n@brief ネットワークSummary用に必要なバッファのサイズを取得します。\n@param net ネットワークオブジェクトポインタ\n@param buffer_size バッファのサイズの格納先(終端null文字分を含む)\n@return\n成功した場合は \\ref AILIA_STATUS_SUCCESS 、そうでなければエラーコードを返す。\n@details\nこのAPIはailiaOpenWeighXXX呼び出し後より利用可能です。","enclosedBy":{"name":"ailiaTokenizerFFI","kind":3,"href":"ailia_tokenizer/ailiaTokenizerFFI-class.html"}},{"name":"ailiaGetVersion","qualifiedName":"ailia_tokenizer.ailiaTokenizerFFI.ailiaGetVersion","href":"ailia_tokenizer/ailiaTokenizerFFI/ailiaGetVersion.html","kind":10,"overriddenDepth":0,"packageRank":0,"desc":"~japanese\n@brief ライブラリバージョンを取得します\n@return\nバージョン番号\n@details\n返値は解放する必要はありません。","enclosedBy":{"name":"ailiaTokenizerFFI","kind":3,"href":"ailia_tokenizer/ailiaTokenizerFFI-class.html"}},{"name":"ailiaOpenStreamEx","qualifiedName":"ailia_tokenizer.ailiaTokenizerFFI.ailiaOpenStreamEx","href":"ailia_tokenizer/ailiaTokenizerFFI/ailiaOpenStreamEx.html","kind":10,"overriddenDepth":0,"packageRank":0,"desc":"~japanese\n@brief ネットワークオブジェクトを初期化します。(ユーザ定義ファイルアクセスコールバック)\n@param net ネットワークオブジェクトポインタ\n@param fopen_args  \\ref AILIA_USER_API_FOPEN に通知される引数ポインタ\n@param callback ユーザ定義ファイルアクセスコールバック関数構造体\n@param version ファイルアクセスコールバック関数構造体のバージョン( \\ref AILIA_FILE_CALLBACK_VERSION )\n@return\n成功した場合は \\ref AILIA_STATUS_SUCCESS 、そうでなければエラーコードを返す。\n@details\nファイルから読み込み、ネットワークオブジェクトを初期化します。","enclosedBy":{"name":"ailiaTokenizerFFI","kind":3,"href":"ailia_tokenizer/ailiaTokenizerFFI-class.html"}},{"name":"ailiaOpenStreamFileA","qualifiedName":"ailia_tokenizer.ailiaTokenizerFFI.ailiaOpenStreamFileA","href":"ailia_tokenizer/ailiaTokenizerFFI/ailiaOpenStreamFileA.html","kind":10,"overriddenDepth":0,"packageRank":0,"desc":"~japanese\n@brief ネットワークオブジェクトを初期化します。(ファイルから読み込み)\n@param net ネットワークオブジェクトポインタ\n@param path prototxtファイルのパス名(MBSC or UTF16)\n@return\n成功した場合は \\ref AILIA_STATUS_SUCCESS 、そうでなければエラーコードを返す。\n@details\nファイルから読み込み、ネットワークオブジェクトを初期化します。","enclosedBy":{"name":"ailiaTokenizerFFI","kind":3,"href":"ailia_tokenizer/ailiaTokenizerFFI-class.html"}},{"name":"ailiaOpenStreamFileW","qualifiedName":"ailia_tokenizer.ailiaTokenizerFFI.ailiaOpenStreamFileW","href":"ailia_tokenizer/ailiaTokenizerFFI/ailiaOpenStreamFileW.html","kind":10,"overriddenDepth":0,"packageRank":0,"desc":"","enclosedBy":{"name":"ailiaTokenizerFFI","kind":3,"href":"ailia_tokenizer/ailiaTokenizerFFI-class.html"}},{"name":"ailiaOpenStreamMem","qualifiedName":"ailia_tokenizer.ailiaTokenizerFFI.ailiaOpenStreamMem","href":"ailia_tokenizer/ailiaTokenizerFFI/ailiaOpenStreamMem.html","kind":10,"overriddenDepth":0,"packageRank":0,"desc":"~japanese\n@brief ネットワークオブジェクトを初期化します。(メモリから読み込み)\n@param net ネットワークオブジェクトポインタ\n@param buf prototxtファイルのデータへのポインタ\n@param buf_size prototxtファイルのデータサイズ\n@return\n成功した場合は \\ref AILIA_STATUS_SUCCESS 、そうでなければエラーコードを返す。\n@details\nメモリから読み込み、ネットワークオブジェクトを初期化します。","enclosedBy":{"name":"ailiaTokenizerFFI","kind":3,"href":"ailia_tokenizer/ailiaTokenizerFFI-class.html"}},{"name":"ailiaOpenWeightEx","qualifiedName":"ailia_tokenizer.ailiaTokenizerFFI.ailiaOpenWeightEx","href":"ailia_tokenizer/ailiaTokenizerFFI/ailiaOpenWeightEx.html","kind":10,"overriddenDepth":0,"packageRank":0,"desc":"~japanese\n@brief ネットワークオブジェクトに重み係数を読み込みます。(ユーザ定義ファイルアクセスコールバック)\n@param net ネットワークオブジェクトポインタ\n@param fopen_args  \\ref AILIA_USER_API_FOPEN に通知される引数ポインタ\n@param callback ユーザ定義ファイルアクセスコールバック関数構造体\n@param version ファイルアクセスコールバック関数構造体のバージョン( \\ref AILIA_FILE_CALLBACK_VERSION )\n@return\n成功した場合は \\ref AILIA_STATUS_SUCCESS 、そうでなければエラーコードを返す。\n@details\nファイルからネットワークオブジェクトに重み係数を読み込みます。","enclosedBy":{"name":"ailiaTokenizerFFI","kind":3,"href":"ailia_tokenizer/ailiaTokenizerFFI-class.html"}},{"name":"ailiaOpenWeightFileA","qualifiedName":"ailia_tokenizer.ailiaTokenizerFFI.ailiaOpenWeightFileA","href":"ailia_tokenizer/ailiaTokenizerFFI/ailiaOpenWeightFileA.html","kind":10,"overriddenDepth":0,"packageRank":0,"desc":"~japanese\n@brief ネットワークオブジェクトに重み係数を読み込みます。(ファイルから読み込み)\n@param net ネットワークオブジェクトポインタ\n@param path protobuf/onnxファイルのパス名(MBSC or UTF16)\n@return\n成功した場合は \\ref AILIA_STATUS_SUCCESS 、そうでなければエラーコードを返す。\n@details\nファイルからネットワークオブジェクトに重み係数を読み込みます。","enclosedBy":{"name":"ailiaTokenizerFFI","kind":3,"href":"ailia_tokenizer/ailiaTokenizerFFI-class.html"}},{"name":"ailiaOpenWeightFileW","qualifiedName":"ailia_tokenizer.ailiaTokenizerFFI.ailiaOpenWeightFileW","href":"ailia_tokenizer/ailiaTokenizerFFI/ailiaOpenWeightFileW.html","kind":10,"overriddenDepth":0,"packageRank":0,"desc":"","enclosedBy":{"name":"ailiaTokenizerFFI","kind":3,"href":"ailia_tokenizer/ailiaTokenizerFFI-class.html"}},{"name":"ailiaOpenWeightMem","qualifiedName":"ailia_tokenizer.ailiaTokenizerFFI.ailiaOpenWeightMem","href":"ailia_tokenizer/ailiaTokenizerFFI/ailiaOpenWeightMem.html","kind":10,"overriddenDepth":0,"packageRank":0,"desc":"~japanese\n@brief ネットワークオブジェクトに重み係数を読み込みます。(メモリから読み込み)\n@param net ネットワークオブジェクトポインタ\n@param buf protobuf/onnxファイルのデータへのポインタ\n@param buf_size protobuf/onnxファイルのデータサイズ\n@return\n成功した場合は \\ref AILIA_STATUS_SUCCESS 、そうでなければエラーコードを返す。\n@details\nメモリからネットワークオブジェクトに重み係数を読み込みます。","enclosedBy":{"name":"ailiaTokenizerFFI","kind":3,"href":"ailia_tokenizer/ailiaTokenizerFFI-class.html"}},{"name":"ailiaPredict","qualifiedName":"ailia_tokenizer.ailiaTokenizerFFI.ailiaPredict","href":"ailia_tokenizer/ailiaTokenizerFFI/ailiaPredict.html","kind":10,"overriddenDepth":0,"packageRank":0,"desc":"~japanese\n@brief 推論を行い推論結果を取得します。\n@param net ネットワークオブジェクトポインタ\n@param dest 推論結果の書き出し先バッファにX,Y,Z,Wの順でnumeric型で格納  サイズはネットファイルのoutputSizeとなる\n@param dest_size 推論結果の書き出し先バッファのbyte数\n@param src 推論データ X,Y,Z,Wの順でnumeric型で格納 サイズはネットファイルのinputSizeとなる\n@param src_size 推論データのbyte数\n@return\n成功した場合は \\ref AILIA_STATUS_SUCCESS 、そうでなければエラーコードを返す。\n@details\nこのAPIはailiaOpenWeighXXX呼び出し後より利用可能です。","enclosedBy":{"name":"ailiaTokenizerFFI","kind":3,"href":"ailia_tokenizer/ailiaTokenizerFFI-class.html"}},{"name":"ailiaSetInputBlobData","qualifiedName":"ailia_tokenizer.ailiaTokenizerFFI.ailiaSetInputBlobData","href":"ailia_tokenizer/ailiaTokenizerFFI/ailiaSetInputBlobData.html","kind":10,"overriddenDepth":0,"packageRank":0,"desc":"~japanese\n@brief 指定したBlobに入力データを与えます。\n@param net ネットワークオブジェクトポインタ\n@param src 推論データ X,Y,Z,Wの順でnumeric型で格納\n@param src_size 推論データのbyte数\n@param blob_idx 入力するblobのインデックス\n@return\n成功した場合は \\ref AILIA_STATUS_SUCCESS 、そうでなければエラーコードを返す。\n@details\n複数入力があるネットワークなどで入力を指定する場合に用います。\nblob_idxで入力レイヤーのblob以外のものを指定した場合、 \\ref AILIA_STATUS_INVALID_ARGUMENT が返ります。\nこのAPIはailiaOpenWeighXXX呼び出し後より利用可能です。","enclosedBy":{"name":"ailiaTokenizerFFI","kind":3,"href":"ailia_tokenizer/ailiaTokenizerFFI-class.html"}},{"name":"ailiaSetInputBlobShape","qualifiedName":"ailia_tokenizer.ailiaTokenizerFFI.ailiaSetInputBlobShape","href":"ailia_tokenizer/ailiaTokenizerFFI/ailiaSetInputBlobShape.html","kind":10,"overriddenDepth":0,"packageRank":0,"desc":"~japanese\n@brief 指定したBlobの形状を変更します。\n@param net ネットワークオブジェクトポインタ\n@param shape 入力データの形状情報\n@param blob_idx 変更するblobのインデックス\n@param version AILIA_SHAPE_VERSION\n@return\n成功した場合は \\ref AILIA_STATUS_SUCCESS 、そうでなければエラーコードを返す。\n@details\n複数入力があるネットワークなどで入力形状を変更する場合に用います。\nblob_idxは入力レイヤーのblob以外のものを指定した場合 \\ref AILIA_STATUS_INVALID_ARGUMENT が返ります。\nその他の注意点は ailiaSetInputShape() の解説を参照してください。\n入力形状のランクが5次元以上の場合は ailiaSetInputBlobShapeND() を利用してください。\nこのAPIはailiaOpenWeighXXX呼び出し後より利用可能です。","enclosedBy":{"name":"ailiaTokenizerFFI","kind":3,"href":"ailia_tokenizer/ailiaTokenizerFFI-class.html"}},{"name":"ailiaSetInputBlobShapeND","qualifiedName":"ailia_tokenizer.ailiaTokenizerFFI.ailiaSetInputBlobShapeND","href":"ailia_tokenizer/ailiaTokenizerFFI/ailiaSetInputBlobShapeND.html","kind":10,"overriddenDepth":0,"packageRank":0,"desc":"~japanese\n@brief 指定したBlobの形状を変更します。\n@param net ネットワークオブジェクトポインタ\n@param shape 入力データの各次元の大きさの配列(dim-1, dim-2, ... ,1, 0)\n@param dim shapeの次元\n@param blob_idx 変更するblobのインデックス\n@return\n成功した場合は \\ref AILIA_STATUS_SUCCESS 、そうでなければエラーコードを返す。\n@details\n複数入力があるネットワークなどで入力形状を変更する場合に用います。\nblob_idxは入力レイヤーのblob以外のものを指定した場合 \\ref AILIA_STATUS_INVALID_ARGUMENT が返ります。\nその他の注意点は ailiaSetInputShapeND() の解説を参照してください。\nこのAPIはailiaOpenWeighXXX呼び出し後より利用可能です。","enclosedBy":{"name":"ailiaTokenizerFFI","kind":3,"href":"ailia_tokenizer/ailiaTokenizerFFI-class.html"}},{"name":"ailiaSetInputShape","qualifiedName":"ailia_tokenizer.ailiaTokenizerFFI.ailiaSetInputShape","href":"ailia_tokenizer/ailiaTokenizerFFI/ailiaSetInputShape.html","kind":10,"overriddenDepth":0,"packageRank":0,"desc":"~japanese\n@brief 推論時の入力データの形状を変更します。\n@param net ネットワークオブジェクトポインタ\n@param shape 入力データの形状情報\n@param version AILIA_SHAPE_VERSION\n@return\n成功した場合は \\ref AILIA_STATUS_SUCCESS 、そうでなければエラーコードを返す。\n@details\nprototxtで定義されている入力形状を変更します。\nprototxtに記述されているランクと同じにする必要があります。\nなお、重み係数の形状が入力形状に依存しているなどによりエラーが返る場合があります。\nprototxtで定義されているランクが4次元未満の場合は未使用の要素に1を設定する必要があります。\nprototxtで定義されているランクが5次元以上の場合は ailiaSetInputShapeND() を利用してください。\nこのAPIはailiaOpenWeighXXX呼び出し後より利用可能です。","enclosedBy":{"name":"ailiaTokenizerFFI","kind":3,"href":"ailia_tokenizer/ailiaTokenizerFFI-class.html"}},{"name":"ailiaSetInputShapeND","qualifiedName":"ailia_tokenizer.ailiaTokenizerFFI.ailiaSetInputShapeND","href":"ailia_tokenizer/ailiaTokenizerFFI/ailiaSetInputShapeND.html","kind":10,"overriddenDepth":0,"packageRank":0,"desc":"~japanese\n@brief 推論時の入力データの形状を変更します。\n@param net ネットワークオブジェクトポインタ\n@param shape 入力データの各次元の大きさの配列(dim-1, dim-2, ... ,1, 0)\n@param dim shapeの次元\n@return\n成功した場合は \\ref AILIA_STATUS_SUCCESS 、そうでなければエラーコードを返す。\n@details\nprototxtで定義されている入力形状を変更します。\nprototxtに記述されているランクと同じにする必要があります。\nなお、重み係数の形状が入力形状に依存しているなどによりエラーが返る場合があります。\nこのAPIはailiaOpenWeighXXX呼び出し後より利用可能です。","enclosedBy":{"name":"ailiaTokenizerFFI","kind":3,"href":"ailia_tokenizer/ailiaTokenizerFFI-class.html"}},{"name":"ailiaSetMemoryMode","qualifiedName":"ailia_tokenizer.ailiaTokenizerFFI.ailiaSetMemoryMode","href":"ailia_tokenizer/ailiaTokenizerFFI/ailiaSetMemoryMode.html","kind":10,"overriddenDepth":0,"packageRank":0,"desc":"~japanese\n@brief 推論時のメモリの使用方針を設定します\n@param net ネットワークオブジェクトポインタ\n@param mode メモリモード(論理和で複数指定可) AILIA_MEMORY_XXX (デフォルト: \\ref AILIA_MEMORY_REDUCE_CONSTANT )\n@return\n成功した場合は \\ref AILIA_STATUS_SUCCESS 、そうでなければエラーコードを返す。\n@details\nメモリの使用方針を変更します。 \\ref AILIA_MEMORY_NO_OPTIMIZATION 以外を指定した場合は、\n推論時に確保する中間バッファーを開放するため、推論時のメモリ使用量を削減することができます。\nailiaCreate() の直後に指定する必要があります。ailiaOpenを呼び出した後は変更することができません。\nなお、中間バッファーを開放するように指定した場合、該当するBlobに対し、 ailiaGetBlobData() を呼び出すと\n\\ref AILIA_STATUS_DATA_HIDDEN エラーが返ります。","enclosedBy":{"name":"ailiaTokenizerFFI","kind":3,"href":"ailia_tokenizer/ailiaTokenizerFFI-class.html"}},{"name":"ailiaSetProfileMode","qualifiedName":"ailia_tokenizer.ailiaTokenizerFFI.ailiaSetProfileMode","href":"ailia_tokenizer/ailiaTokenizerFFI/ailiaSetProfileMode.html","kind":10,"overriddenDepth":0,"packageRank":0,"desc":"~japanese\n@brief プロファイルモードをセットします\n@param net          ネットワークオブジェクトポインタ\n@param mode         プロファイルモード\n@return\n成功した場合は \\ref AILIA_STATUS_SUCCESS 、そうでなければエラーコードを返す。\n@details\nプロファイルモードを指定します。デフォルトは無効です。\nailiaOpenStreamXXXを呼び出したあとに呼び出してください。\nプロファイルモードを有効にした場合、 ailiaSummary() の出力にプロファイル結果が追加されます。","enclosedBy":{"name":"ailiaTokenizerFFI","kind":3,"href":"ailia_tokenizer/ailiaTokenizerFFI-class.html"}},{"name":"ailiaSetTemporaryCachePathA","qualifiedName":"ailia_tokenizer.ailiaTokenizerFFI.ailiaSetTemporaryCachePathA","href":"ailia_tokenizer/ailiaTokenizerFFI/ailiaSetTemporaryCachePathA.html","kind":10,"overriddenDepth":0,"packageRank":0,"desc":"~japanese\n@brief 一時キャッシュディレクトリを指定します\n@param cache_dir 一時キャッシュディレクトリ\n@return\n成功した場合は \\ref AILIA_STATUS_SUCCESS 、そうでなければエラーコードを返す。\n@details\n指定したキャッシュディレクトリは推論実行環境毎に最適化したマシンコードを生成して保存するためにシステムが利用します。\nailia の実行開始時に一度だけ呼び出してください。二回目以降の呼び出しに対しては無視して成功を返します。\n複数スレッドから呼び出された場合も内部で排他制御しているので特に問題は発生しません。\nVulkan のシェーダーキャッシュ機能など、この API を呼ぶまで利用できないものがあります。\ncache_dirにはContext.getCacheDir()で取得したファイルパスを指定してください。","enclosedBy":{"name":"ailiaTokenizerFFI","kind":3,"href":"ailia_tokenizer/ailiaTokenizerFFI-class.html"}},{"name":"ailiaSetTemporaryCachePathW","qualifiedName":"ailia_tokenizer.ailiaTokenizerFFI.ailiaSetTemporaryCachePathW","href":"ailia_tokenizer/ailiaTokenizerFFI/ailiaSetTemporaryCachePathW.html","kind":10,"overriddenDepth":0,"packageRank":0,"desc":"","enclosedBy":{"name":"ailiaTokenizerFFI","kind":3,"href":"ailia_tokenizer/ailiaTokenizerFFI-class.html"}},{"name":"ailiaSummary","qualifiedName":"ailia_tokenizer.ailiaTokenizerFFI.ailiaSummary","href":"ailia_tokenizer/ailiaTokenizerFFI/ailiaSummary.html","kind":10,"overriddenDepth":0,"packageRank":0,"desc":"~japanese\n@brief 各Blobの名前と形状を表示します。\n@param net ネットワークオブジェクトポインタ\n@param buffer Summaryの出力先\n@param buffer_size 出力バッファのサイズ(終端null文字分を含む)。 ailiaGetSummaryLength()\nで取得した値を設定してください。\n@return\n成功した場合は \\ref AILIA_STATUS_SUCCESS 、そうでなければエラーコードを返す。\n@details\nこのAPIはailiaOpenWeighXXX呼び出し後より利用可能です。","enclosedBy":{"name":"ailiaTokenizerFFI","kind":3,"href":"ailia_tokenizer/ailiaTokenizerFFI-class.html"}},{"name":"ailiaTokenizerAddSpecialTokens","qualifiedName":"ailia_tokenizer.ailiaTokenizerFFI.ailiaTokenizerAddSpecialTokens","href":"ailia_tokenizer/ailiaTokenizerFFI/ailiaTokenizerAddSpecialTokens.html","kind":10,"overriddenDepth":0,"packageRank":0,"desc":"~japanese\n@brief SpecialTokenの追加を行います。\n@param net トークナイザオブジェクトポインタ\n@param tokens トークン(UTF8)\n@param count 追加する個数\n@return\n成功した場合は \\ref AILIA_STATUS_SUCCESS 、そうでなければエラーコードを返す。\n@details\nAILIA_TOKENIZER_TYPE_ROBERTAおよびAILIA_TOKENIZER_TYPE_GPT2の場合のみ有効です。","enclosedBy":{"name":"ailiaTokenizerFFI","kind":3,"href":"ailia_tokenizer/ailiaTokenizerFFI-class.html"}},{"name":"ailiaTokenizerCreate","qualifiedName":"ailia_tokenizer.ailiaTokenizerFFI.ailiaTokenizerCreate","href":"ailia_tokenizer/ailiaTokenizerFFI/ailiaTokenizerCreate.html","kind":10,"overriddenDepth":0,"packageRank":0,"desc":"~japanese\n@brief トークナイズオブジェクトを作成します。\n@param net トークナイザオブジェクトポインタへのポインタ\n@param type AILIA_TOKENIZER_TYPE_*\n@param flag AILIA_TOKENIZER_FLAG_*の論理和\n@return\n成功した場合は \\ref AILIA_STATUS_SUCCESS 、そうでなければエラーコードを返す。\n@details\nトークナイズオブジェクトを作成します。","enclosedBy":{"name":"ailiaTokenizerFFI","kind":3,"href":"ailia_tokenizer/ailiaTokenizerFFI-class.html"}},{"name":"ailiaTokenizerDecode","qualifiedName":"ailia_tokenizer.ailiaTokenizerFFI.ailiaTokenizerDecode","href":"ailia_tokenizer/ailiaTokenizerFFI/ailiaTokenizerDecode.html","kind":10,"overriddenDepth":0,"packageRank":0,"desc":"~japanese\n@brief デコードを行います。\n@param net トークナイザオブジェクトポインタ\n@param tokens デコードするトークン\n@param token_count トークンの数\n@return\n成功した場合は \\ref AILIA_STATUS_SUCCESS 、そうでなければエラーコードを返す。\n@details\nデコードした結果はailiaTokenizerGetText APIで取得します。\nskip_special_tokens=Trueと同様に、Special Tokenは出力しません。","enclosedBy":{"name":"ailiaTokenizerFFI","kind":3,"href":"ailia_tokenizer/ailiaTokenizerFFI-class.html"}},{"name":"ailiaTokenizerDecodeWithSpecialTokens","qualifiedName":"ailia_tokenizer.ailiaTokenizerFFI.ailiaTokenizerDecodeWithSpecialTokens","href":"ailia_tokenizer/ailiaTokenizerFFI/ailiaTokenizerDecodeWithSpecialTokens.html","kind":10,"overriddenDepth":0,"packageRank":0,"desc":"~japanese\n@brief スペシャルトークンを含んだデコードを行います。\n@param net トークナイザオブジェクトポインタ\n@param tokens デコードするトークン\n@param token_count トークンの数\n@return\n成功した場合は \\ref AILIA_STATUS_SUCCESS 、そうでなければエラーコードを返す。\n@details\nデコードした結果はailiaTokenizerGetText APIで取得します。\nskip_special_tokens=Falseと同様に、Special Tokenを出力します。","enclosedBy":{"name":"ailiaTokenizerFFI","kind":3,"href":"ailia_tokenizer/ailiaTokenizerFFI-class.html"}},{"name":"ailiaTokenizerDestroy","qualifiedName":"ailia_tokenizer.ailiaTokenizerFFI.ailiaTokenizerDestroy","href":"ailia_tokenizer/ailiaTokenizerFFI/ailiaTokenizerDestroy.html","kind":10,"overriddenDepth":0,"packageRank":0,"desc":"~japanese\n@brief トークナイズオブジェクトを破棄します。\n@param net トークナイザオブジェクトポインタ","enclosedBy":{"name":"ailiaTokenizerFFI","kind":3,"href":"ailia_tokenizer/ailiaTokenizerFFI-class.html"}},{"name":"ailiaTokenizerEncode","qualifiedName":"ailia_tokenizer.ailiaTokenizerFFI.ailiaTokenizerEncode","href":"ailia_tokenizer/ailiaTokenizerFFI/ailiaTokenizerEncode.html","kind":10,"overriddenDepth":0,"packageRank":0,"desc":"~japanese\n@brief エンコードを行います。\n@param net トークナイザオブジェクトポインタ\n@param text エンコードするテキスト(UTF8)\n@return\n成功した場合は \\ref AILIA_STATUS_SUCCESS 、そうでなければエラーコードを返す。\n@details\n認識した結果はailiaTokenizerGetTokens APIで取得します。\nsplit_special_tokens=Trueと同様に、Special Tokenは分割して文字列として扱われます。","enclosedBy":{"name":"ailiaTokenizerFFI","kind":3,"href":"ailia_tokenizer/ailiaTokenizerFFI-class.html"}},{"name":"ailiaTokenizerEncodeWithSpecialTokens","qualifiedName":"ailia_tokenizer.ailiaTokenizerFFI.ailiaTokenizerEncodeWithSpecialTokens","href":"ailia_tokenizer/ailiaTokenizerFFI/ailiaTokenizerEncodeWithSpecialTokens.html","kind":10,"overriddenDepth":0,"packageRank":0,"desc":"~japanese\n@brief スペシャルトークンを含んだエンコードを行います。\n@param net トークナイザオブジェクトポインタ\n@param text エンコードするテキスト(UTF8)\n@return\n成功した場合は \\ref AILIA_STATUS_SUCCESS 、そうでなければエラーコードを返す。\n@details\n認識した結果はailiaTokenizerGetTokens APIで取得します。\nsplit_special_tokens=Falseと同様に、Special Tokenを出力します。","enclosedBy":{"name":"ailiaTokenizerFFI","kind":3,"href":"ailia_tokenizer/ailiaTokenizerFFI-class.html"}},{"name":"ailiaTokenizerFFI.fromLookup","qualifiedName":"ailia_tokenizer.ailiaTokenizerFFI.ailiaTokenizerFFI.fromLookup","href":"ailia_tokenizer/ailiaTokenizerFFI/ailiaTokenizerFFI.fromLookup.html","kind":2,"packageRank":0,"desc":"The symbols are looked up with lookup.","enclosedBy":{"name":"ailiaTokenizerFFI","kind":3,"href":"ailia_tokenizer/ailiaTokenizerFFI-class.html"}},{"name":"ailiaTokenizerFFI.new","qualifiedName":"ailia_tokenizer.ailiaTokenizerFFI.ailiaTokenizerFFI.new","href":"ailia_tokenizer/ailiaTokenizerFFI/ailiaTokenizerFFI.html","kind":2,"packageRank":0,"desc":"The symbols are looked up in dynamicLibrary.","enclosedBy":{"name":"ailiaTokenizerFFI","kind":3,"href":"ailia_tokenizer/ailiaTokenizerFFI-class.html"}},{"name":"ailiaTokenizerGetCharEnds","qualifiedName":"ailia_tokenizer.ailiaTokenizerFFI.ailiaTokenizerGetCharEnds","href":"ailia_tokenizer/ailiaTokenizerFFI/ailiaTokenizerGetCharEnds.html","kind":10,"overriddenDepth":0,"packageRank":0,"desc":"~japanese\n@brief 終了文字位置を取得します。\n@param net   トークナイザオブジェクトポインタ\n@param char_ends 終了文字位置\n@param count  格納先トークン数\n@param\n@return\n成功した場合は \\ref AILIA_STATUS_SUCCESS 、そうでなければエラーコードを返す。\n@details\nailiaTokenizerEncode() を一度も実行していない場合は \\ref AILIA_STATUS_INVALID_STATE が返ります。\nAILIA_TOKENIZER_TYPE_ROBERTAとAILIA_TOKENIZER_TYPE_BERTの場合のみ有効です。\n各トークンに対応するUTF32単位での終了文字位置が返ります。","enclosedBy":{"name":"ailiaTokenizerFFI","kind":3,"href":"ailia_tokenizer/ailiaTokenizerFFI-class.html"}},{"name":"ailiaTokenizerGetCharStarts","qualifiedName":"ailia_tokenizer.ailiaTokenizerFFI.ailiaTokenizerGetCharStarts","href":"ailia_tokenizer/ailiaTokenizerFFI/ailiaTokenizerGetCharStarts.html","kind":10,"overriddenDepth":0,"packageRank":0,"desc":"~japanese\n@brief 開始文字位置を取得します。\n@param net   トークナイザオブジェクトポインタ\n@param char_starts 開始文字位置\n@param count  格納先トークン数\n@param\n@return\n成功した場合は \\ref AILIA_STATUS_SUCCESS 、そうでなければエラーコードを返す。\n@details\nailiaTokenizerEncode() を一度も実行していない場合は \\ref AILIA_STATUS_INVALID_STATE が返ります。\nAILIA_TOKENIZER_TYPE_ROBERTAとAILIA_TOKENIZER_TYPE_BERTの場合のみ有効です。\n各トークンに対応するUTF32単位での開始文字位置が返ります。","enclosedBy":{"name":"ailiaTokenizerFFI","kind":3,"href":"ailia_tokenizer/ailiaTokenizerFFI-class.html"}},{"name":"ailiaTokenizerGetText","qualifiedName":"ailia_tokenizer.ailiaTokenizerFFI.ailiaTokenizerGetText","href":"ailia_tokenizer/ailiaTokenizerFFI/ailiaTokenizerGetText.html","kind":10,"overriddenDepth":0,"packageRank":0,"desc":"~japanese\n@brief テキストを取得します。\n@param net   トークナイザオブジェクトポインタ\n@param text  テキスト(UTF8)\n@param len バッファサイズ\n@return\n成功した場合は \\ref AILIA_STATUS_SUCCESS 、そうでなければエラーコードを返す。\n@details\nailiaTokenizerDecode() を一度も実行していない場合は \\ref AILIA_STATUS_INVALID_STATE が返ります。","enclosedBy":{"name":"ailiaTokenizerFFI","kind":3,"href":"ailia_tokenizer/ailiaTokenizerFFI-class.html"}},{"name":"ailiaTokenizerGetTextLength","qualifiedName":"ailia_tokenizer.ailiaTokenizerFFI.ailiaTokenizerGetTextLength","href":"ailia_tokenizer/ailiaTokenizerFFI/ailiaTokenizerGetTextLength.html","kind":10,"overriddenDepth":0,"packageRank":0,"desc":"~japanese\n@brief テキストの長さを取得します。(NULL文字含む)\n@param net   トークナイザオブジェクトポインタ\n@param len  テキストの長さ\n@return\n成功した場合は \\ref AILIA_STATUS_SUCCESS 、そうでなければエラーコードを返す。","enclosedBy":{"name":"ailiaTokenizerFFI","kind":3,"href":"ailia_tokenizer/ailiaTokenizerFFI-class.html"}},{"name":"ailiaTokenizerGetTokenCount","qualifiedName":"ailia_tokenizer.ailiaTokenizerFFI.ailiaTokenizerGetTokenCount","href":"ailia_tokenizer/ailiaTokenizerFFI/ailiaTokenizerGetTokenCount.html","kind":10,"overriddenDepth":0,"packageRank":0,"desc":"~japanese\n@brief トークンの数を取得します。\n@param net   トークナイザオブジェクトポインタ\n@param count  オブジェクト数\n@return\n成功した場合は \\ref AILIA_STATUS_SUCCESS 、そうでなければエラーコードを返す。","enclosedBy":{"name":"ailiaTokenizerFFI","kind":3,"href":"ailia_tokenizer/ailiaTokenizerFFI-class.html"}},{"name":"ailiaTokenizerGetTokens","qualifiedName":"ailia_tokenizer.ailiaTokenizerFFI.ailiaTokenizerGetTokens","href":"ailia_tokenizer/ailiaTokenizerFFI/ailiaTokenizerGetTokens.html","kind":10,"overriddenDepth":0,"packageRank":0,"desc":"~japanese\n@brief トークンを取得します。\n@param net   トークナイザオブジェクトポインタ\n@param tokens トークン\n@param count  格納先トークン数\n@param\n@return\n成功した場合は \\ref AILIA_STATUS_SUCCESS 、そうでなければエラーコードを返す。\n@details\nailiaTokenizerEncode() を一度も実行していない場合は \\ref AILIA_STATUS_INVALID_STATE が返ります。","enclosedBy":{"name":"ailiaTokenizerFFI","kind":3,"href":"ailia_tokenizer/ailiaTokenizerFFI-class.html"}},{"name":"ailiaTokenizerGetVocab","qualifiedName":"ailia_tokenizer.ailiaTokenizerFFI.ailiaTokenizerGetVocab","href":"ailia_tokenizer/ailiaTokenizerFFI/ailiaTokenizerGetVocab.html","kind":10,"overriddenDepth":0,"packageRank":0,"desc":"~japanese\n@brief Vocabの取得を行います。\n@param net トークナイザオブジェクトポインタ\n@param token トークン\n@param vocab Vocabのテキスト(UTF8)\n@return\n成功した場合は \\ref AILIA_STATUS_SUCCESS 、そうでなければエラーコードを返す。\n@details\nvocabを解放する必要はありません。\nvocabの有効期間は次にailiaTokenizer APIを呼び出すまでになります。","enclosedBy":{"name":"ailiaTokenizerFFI","kind":3,"href":"ailia_tokenizer/ailiaTokenizerFFI-class.html"}},{"name":"ailiaTokenizerGetVocabSize","qualifiedName":"ailia_tokenizer.ailiaTokenizerFFI.ailiaTokenizerGetVocabSize","href":"ailia_tokenizer/ailiaTokenizerFFI/ailiaTokenizerGetVocabSize.html","kind":10,"overriddenDepth":0,"packageRank":0,"desc":"~japanese\n@brief Vocabの数を取得します。\n@param net   トークナイザオブジェクトポインタ\n@param size  Vocabの要素数\n@return\n成功した場合は \\ref AILIA_STATUS_SUCCESS 、そうでなければエラーコードを返す。","enclosedBy":{"name":"ailiaTokenizerFFI","kind":3,"href":"ailia_tokenizer/ailiaTokenizerFFI-class.html"}},{"name":"ailiaTokenizerGetWordIDs","qualifiedName":"ailia_tokenizer.ailiaTokenizerFFI.ailiaTokenizerGetWordIDs","href":"ailia_tokenizer/ailiaTokenizerFFI/ailiaTokenizerGetWordIDs.html","kind":10,"overriddenDepth":0,"packageRank":0,"desc":"~japanese\n@brief ワードIDを取得します。\n@param net   トークナイザオブジェクトポインタ\n@param word_ids ワードID\n@param count  格納先トークン数\n@param\n@return\n成功した場合は \\ref AILIA_STATUS_SUCCESS 、そうでなければエラーコードを返す。\n@details\nailiaTokenizerEncode() を一度も実行していない場合は \\ref AILIA_STATUS_INVALID_STATE が返ります。\nAILIA_TOKENIZER_TYPE_ROBERTAとAILIA_TOKENIZER_TYPE_BERTの場合のみ有効です。","enclosedBy":{"name":"ailiaTokenizerFFI","kind":3,"href":"ailia_tokenizer/ailiaTokenizerFFI-class.html"}},{"name":"ailiaTokenizerOpenAddedTokensFileA","qualifiedName":"ailia_tokenizer.ailiaTokenizerFFI.ailiaTokenizerOpenAddedTokensFileA","href":"ailia_tokenizer/ailiaTokenizerFFI/ailiaTokenizerOpenAddedTokensFileA.html","kind":10,"overriddenDepth":0,"packageRank":0,"desc":"~japanese\n@brief 追加トークンファイルを読み込みます。\n@param net トークナイザオブジェクトポインタへのポインタ\n@param path スペシャルトークンファイルのパス\n@return\n成功した場合は \\ref AILIA_STATUS_SUCCESS 、そうでなければエラーコードを返す。\n@details\n追加トークンファイル (json) を読み込みます。AILIA_TOKENIZER_TYPE_WHISPERもしくはAILIA_TOKENIZER_TYPE_XLM_ROBERTAの場合のみ有効です。","enclosedBy":{"name":"ailiaTokenizerFFI","kind":3,"href":"ailia_tokenizer/ailiaTokenizerFFI-class.html"}},{"name":"ailiaTokenizerOpenAddedTokensFileW","qualifiedName":"ailia_tokenizer.ailiaTokenizerFFI.ailiaTokenizerOpenAddedTokensFileW","href":"ailia_tokenizer/ailiaTokenizerFFI/ailiaTokenizerOpenAddedTokensFileW.html","kind":10,"overriddenDepth":0,"packageRank":0,"desc":"","enclosedBy":{"name":"ailiaTokenizerFFI","kind":3,"href":"ailia_tokenizer/ailiaTokenizerFFI-class.html"}},{"name":"ailiaTokenizerOpenDictionaryFileA","qualifiedName":"ailia_tokenizer.ailiaTokenizerFFI.ailiaTokenizerOpenDictionaryFileA","href":"ailia_tokenizer/ailiaTokenizerFFI/ailiaTokenizerOpenDictionaryFileA.html","kind":10,"overriddenDepth":0,"packageRank":0,"desc":"~japanese\n@brief 辞書ファイルを読み込みます。\n@param net トークナイザオブジェクトポインタへのポインタ\n@param path Mecabの辞書ファイルのパス\n@return\n成功した場合は \\ref AILIA_STATUS_SUCCESS 、そうでなければエラーコードを返す。\n@details\nMecabの辞書ファイルを読み込みます。AILIA_TOKENIZER_TYPE_BERT_JAPANESE_XXXの場合のみ必要です。","enclosedBy":{"name":"ailiaTokenizerFFI","kind":3,"href":"ailia_tokenizer/ailiaTokenizerFFI-class.html"}},{"name":"ailiaTokenizerOpenDictionaryFileW","qualifiedName":"ailia_tokenizer.ailiaTokenizerFFI.ailiaTokenizerOpenDictionaryFileW","href":"ailia_tokenizer/ailiaTokenizerFFI/ailiaTokenizerOpenDictionaryFileW.html","kind":10,"overriddenDepth":0,"packageRank":0,"desc":"","enclosedBy":{"name":"ailiaTokenizerFFI","kind":3,"href":"ailia_tokenizer/ailiaTokenizerFFI-class.html"}},{"name":"ailiaTokenizerOpenMergeFileA","qualifiedName":"ailia_tokenizer.ailiaTokenizerFFI.ailiaTokenizerOpenMergeFileA","href":"ailia_tokenizer/ailiaTokenizerFFI/ailiaTokenizerOpenMergeFileA.html","kind":10,"overriddenDepth":0,"packageRank":0,"desc":"~japanese\n@brief マージファイルを読み込みます。\n@param net トークナイザオブジェクトポインタへのポインタ\n@param path マージファイルのパス\n@return\n成功した場合は \\ref AILIA_STATUS_SUCCESS 、そうでなければエラーコードを返す。\n@details\nマージファイル (txt) を読み込みます。AILIA_TOKENIZER_TYPE_ROBERTAもしくはAILIA_TOKENIZER_TYPE_WHISPERもしくはAILIA_TOKENIZER_TYPE_GPT2の場合のみ有効です。","enclosedBy":{"name":"ailiaTokenizerFFI","kind":3,"href":"ailia_tokenizer/ailiaTokenizerFFI-class.html"}},{"name":"ailiaTokenizerOpenMergeFileW","qualifiedName":"ailia_tokenizer.ailiaTokenizerFFI.ailiaTokenizerOpenMergeFileW","href":"ailia_tokenizer/ailiaTokenizerFFI/ailiaTokenizerOpenMergeFileW.html","kind":10,"overriddenDepth":0,"packageRank":0,"desc":"","enclosedBy":{"name":"ailiaTokenizerFFI","kind":3,"href":"ailia_tokenizer/ailiaTokenizerFFI-class.html"}},{"name":"ailiaTokenizerOpenModelFileA","qualifiedName":"ailia_tokenizer.ailiaTokenizerFFI.ailiaTokenizerOpenModelFileA","href":"ailia_tokenizer/ailiaTokenizerFFI/ailiaTokenizerOpenModelFileA.html","kind":10,"overriddenDepth":0,"packageRank":0,"desc":"~japanese\n@brief モデルファイルを読み込みます。\n@param net トークナイザオブジェクトポインタへのポインタ\n@param path SentencePieceのモデルファイルのパス\n@return\n成功した場合は \\ref AILIA_STATUS_SUCCESS 、そうでなければエラーコードを返す。\n@details\nSentencePieceのモデルファイルを読み込みます。AILIA_TOKENIZER_TYPE_XLM_ROBERTAもしくはAILIA_TOKENIZER_TYPE_MARIANの場合のみ必要です。","enclosedBy":{"name":"ailiaTokenizerFFI","kind":3,"href":"ailia_tokenizer/ailiaTokenizerFFI-class.html"}},{"name":"ailiaTokenizerOpenModelFileW","qualifiedName":"ailia_tokenizer.ailiaTokenizerFFI.ailiaTokenizerOpenModelFileW","href":"ailia_tokenizer/ailiaTokenizerFFI/ailiaTokenizerOpenModelFileW.html","kind":10,"overriddenDepth":0,"packageRank":0,"desc":"","enclosedBy":{"name":"ailiaTokenizerFFI","kind":3,"href":"ailia_tokenizer/ailiaTokenizerFFI-class.html"}},{"name":"ailiaTokenizerOpenTokenizerConfigFileA","qualifiedName":"ailia_tokenizer.ailiaTokenizerFFI.ailiaTokenizerOpenTokenizerConfigFileA","href":"ailia_tokenizer/ailiaTokenizerFFI/ailiaTokenizerOpenTokenizerConfigFileA.html","kind":10,"overriddenDepth":0,"packageRank":0,"desc":"~japanese\n@brief コンフィグファイルを読み込みます。\n@param net トークナイザオブジェクトポインタへのポインタ\n@param path コンフィグファイルのパス\n@return\n成功した場合は \\ref AILIA_STATUS_SUCCESS 、そうでなければエラーコードを返す。\n@details\nトークナイザコンフィグファイル (json) を読み込みます。AILIA_TOKENIZER_TYPE_BERTの場合のみ有効です。","enclosedBy":{"name":"ailiaTokenizerFFI","kind":3,"href":"ailia_tokenizer/ailiaTokenizerFFI-class.html"}},{"name":"ailiaTokenizerOpenTokenizerConfigFileW","qualifiedName":"ailia_tokenizer.ailiaTokenizerFFI.ailiaTokenizerOpenTokenizerConfigFileW","href":"ailia_tokenizer/ailiaTokenizerFFI/ailiaTokenizerOpenTokenizerConfigFileW.html","kind":10,"overriddenDepth":0,"packageRank":0,"desc":"","enclosedBy":{"name":"ailiaTokenizerFFI","kind":3,"href":"ailia_tokenizer/ailiaTokenizerFFI-class.html"}},{"name":"ailiaTokenizerOpenVocabFileA","qualifiedName":"ailia_tokenizer.ailiaTokenizerFFI.ailiaTokenizerOpenVocabFileA","href":"ailia_tokenizer/ailiaTokenizerFFI/ailiaTokenizerOpenVocabFileA.html","kind":10,"overriddenDepth":0,"packageRank":0,"desc":"~japanese\n@brief 単語ファイルを読み込みます。\n@param net トークナイザオブジェクトポインタへのポインタ\n@param path 単語ファイルのパス\n@return\n成功した場合は \\ref AILIA_STATUS_SUCCESS 、そうでなければエラーコードを返す。\n@details\n単語ファイル (ROBERTAとWHISPERとGPT2はjson、それ以外はtxt) を読み込みます。","enclosedBy":{"name":"ailiaTokenizerFFI","kind":3,"href":"ailia_tokenizer/ailiaTokenizerFFI-class.html"}},{"name":"ailiaTokenizerOpenVocabFileW","qualifiedName":"ailia_tokenizer.ailiaTokenizerFFI.ailiaTokenizerOpenVocabFileW","href":"ailia_tokenizer/ailiaTokenizerFFI/ailiaTokenizerOpenVocabFileW.html","kind":10,"overriddenDepth":0,"packageRank":0,"desc":"","enclosedBy":{"name":"ailiaTokenizerFFI","kind":3,"href":"ailia_tokenizer/ailiaTokenizerFFI-class.html"}},{"name":"ailiaTokenizerUtf8ToUtf32","qualifiedName":"ailia_tokenizer.ailiaTokenizerFFI.ailiaTokenizerUtf8ToUtf32","href":"ailia_tokenizer/ailiaTokenizerFFI/ailiaTokenizerUtf8ToUtf32.html","kind":10,"overriddenDepth":0,"packageRank":0,"desc":"~japanese\n@brief UTF8の文字をUTF32の文字に変換します。\n@param utf32   UTF32の文字\n@param processed_byte 消費したバイト数(UTF8)\n@param utf8  UTF8の文字\n@param utf8_len   バッファサイズ\n@return\n成功した場合は \\ref AILIA_STATUS_SUCCESS 、そうでなければエラーコードを返す。","enclosedBy":{"name":"ailiaTokenizerFFI","kind":3,"href":"ailia_tokenizer/ailiaTokenizerFFI-class.html"}},{"name":"ailiaTokenizerUtf32ToUtf8","qualifiedName":"ailia_tokenizer.ailiaTokenizerFFI.ailiaTokenizerUtf32ToUtf8","href":"ailia_tokenizer/ailiaTokenizerFFI/ailiaTokenizerUtf32ToUtf8.html","kind":10,"overriddenDepth":0,"packageRank":0,"desc":"~japanese\n@brief UTF32の文字をUTF8の文字に変換します。\n@param utf8   UTF8の文字(4byte以上必要)\n@param processed_byte 書き込んだ文字数(UTF8)\n@param utf32  UTF32の文字\n@return\n成功した場合は \\ref AILIA_STATUS_SUCCESS 、そうでなければエラーコードを返す。","enclosedBy":{"name":"ailiaTokenizerFFI","kind":3,"href":"ailia_tokenizer/ailiaTokenizerFFI-class.html"}},{"name":"ailiaUpdate","qualifiedName":"ailia_tokenizer.ailiaTokenizerFFI.ailiaUpdate","href":"ailia_tokenizer/ailiaTokenizerFFI/ailiaUpdate.html","kind":10,"overriddenDepth":0,"packageRank":0,"desc":"~japanese\n@brief 事前に指定した入力データで推論を行います。\n@param net ネットワークオブジェクトポインタ\n@return\n成功した場合は \\ref AILIA_STATUS_SUCCESS 、そうでなければエラーコードを返す。\n@details\nailiaSetInputBlobData() を用いて入力を与えた場合などに用います。\n推論結果は ailiaGetBlobData() で取得してください。\nこのAPIはailiaOpenWeighXXX呼び出し後より利用可能です。","enclosedBy":{"name":"ailiaTokenizerFFI","kind":3,"href":"ailia_tokenizer/ailiaTokenizerFFI-class.html"}},{"name":"ailia_tokenizer_model","qualifiedName":"ailia_tokenizer_model","href":"ailia_tokenizer_model/","kind":9,"packageRank":0,"desc":""},{"name":"AiliaTokenizerModel","qualifiedName":"ailia_tokenizer_model.AiliaTokenizerModel","href":"ailia_tokenizer_model/AiliaTokenizerModel-class.html","kind":3,"packageRank":0,"desc":"","enclosedBy":{"name":"ailia_tokenizer_model","kind":9,"href":"ailia_tokenizer_model/"}},{"name":"AiliaTokenizerModel.new","qualifiedName":"ailia_tokenizer_model.AiliaTokenizerModel.AiliaTokenizerModel.new","href":"ailia_tokenizer_model/AiliaTokenizerModel/AiliaTokenizerModel.html","kind":2,"packageRank":0,"desc":"","enclosedBy":{"name":"AiliaTokenizerModel","kind":3,"href":"ailia_tokenizer_model/AiliaTokenizerModel-class.html"}},{"name":"addSpecialTokens","qualifiedName":"ailia_tokenizer_model.AiliaTokenizerModel.addSpecialTokens","href":"ailia_tokenizer_model/AiliaTokenizerModel/addSpecialTokens.html","kind":10,"overriddenDepth":0,"packageRank":0,"desc":"","enclosedBy":{"name":"AiliaTokenizerModel","kind":3,"href":"ailia_tokenizer_model/AiliaTokenizerModel-class.html"}},{"name":"ailiaCommonGetLibrary","qualifiedName":"ailia_tokenizer_model.AiliaTokenizerModel.ailiaCommonGetLibrary","href":"ailia_tokenizer_model/AiliaTokenizerModel/ailiaCommonGetLibrary.html","kind":10,"overriddenDepth":0,"packageRank":0,"desc":"","enclosedBy":{"name":"AiliaTokenizerModel","kind":3,"href":"ailia_tokenizer_model/AiliaTokenizerModel-class.html"}},{"name":"ailiaCommonGetTokenizerPath","qualifiedName":"ailia_tokenizer_model.AiliaTokenizerModel.ailiaCommonGetTokenizerPath","href":"ailia_tokenizer_model/AiliaTokenizerModel/ailiaCommonGetTokenizerPath.html","kind":10,"overriddenDepth":0,"packageRank":0,"desc":"","enclosedBy":{"name":"AiliaTokenizerModel","kind":3,"href":"ailia_tokenizer_model/AiliaTokenizerModel-class.html"}},{"name":"ailiaStatusSuccess","qualifiedName":"ailia_tokenizer_model.AiliaTokenizerModel.ailiaStatusSuccess","href":"ailia_tokenizer_model/AiliaTokenizerModel/ailiaStatusSuccess.html","kind":16,"overriddenDepth":0,"packageRank":0,"desc":"","enclosedBy":{"name":"AiliaTokenizerModel","kind":3,"href":"ailia_tokenizer_model/AiliaTokenizerModel-class.html"}},{"name":"ailiaTokenizer","qualifiedName":"ailia_tokenizer_model.AiliaTokenizerModel.ailiaTokenizer","href":"ailia_tokenizer_model/AiliaTokenizerModel/ailiaTokenizer.html","kind":16,"overriddenDepth":0,"packageRank":0,"desc":"","enclosedBy":{"name":"AiliaTokenizerModel","kind":3,"href":"ailia_tokenizer_model/AiliaTokenizerModel-class.html"}},{"name":"available","qualifiedName":"ailia_tokenizer_model.AiliaTokenizerModel.available","href":"ailia_tokenizer_model/AiliaTokenizerModel/available.html","kind":16,"overriddenDepth":0,"packageRank":0,"desc":"","enclosedBy":{"name":"AiliaTokenizerModel","kind":3,"href":"ailia_tokenizer_model/AiliaTokenizerModel-class.html"}},{"name":"close","qualifiedName":"ailia_tokenizer_model.AiliaTokenizerModel.close","href":"ailia_tokenizer_model/AiliaTokenizerModel/close.html","kind":10,"overriddenDepth":0,"packageRank":0,"desc":"","enclosedBy":{"name":"AiliaTokenizerModel","kind":3,"href":"ailia_tokenizer_model/AiliaTokenizerModel-class.html"}},{"name":"encode","qualifiedName":"ailia_tokenizer_model.AiliaTokenizerModel.encode","href":"ailia_tokenizer_model/AiliaTokenizerModel/encode.html","kind":10,"overriddenDepth":0,"packageRank":0,"desc":"","enclosedBy":{"name":"AiliaTokenizerModel","kind":3,"href":"ailia_tokenizer_model/AiliaTokenizerModel-class.html"}},{"name":"openFile","qualifiedName":"ailia_tokenizer_model.AiliaTokenizerModel.openFile","href":"ailia_tokenizer_model/AiliaTokenizerModel/openFile.html","kind":10,"overriddenDepth":0,"packageRank":0,"desc":"","enclosedBy":{"name":"AiliaTokenizerModel","kind":3,"href":"ailia_tokenizer_model/AiliaTokenizerModel-class.html"}},{"name":"ppAiliaTokenizer","qualifiedName":"ailia_tokenizer_model.AiliaTokenizerModel.ppAiliaTokenizer","href":"ailia_tokenizer_model/AiliaTokenizerModel/ppAiliaTokenizer.html","kind":16,"overriddenDepth":0,"packageRank":0,"desc":"","enclosedBy":{"name":"AiliaTokenizerModel","kind":3,"href":"ailia_tokenizer_model/AiliaTokenizerModel-class.html"}}]
